[
  {
    "title": "1.1. «Երկաթուղային գծանց` ուղեփակոցով»",
    "description": "1.1. «Երկաթուղային գծանց` ուղեփակոցով»",
    "imageUrl": "https://varord.am/images/sign/n1/1_1.png",
    "type": "1. ՆԱԽԱԶԳՈՒՇԱՑՆՈՂ ՆՇԱՆՆԵՐ"
  },
  {
    "title": "1.2. «Երկաթուղային գծանց` առանց ուղեփակոցի»",
    "description": "1.2. «Երկաթուղային գծանց` առանց ուղեփակոցի»",
    "imageUrl": "https://varord.am/images/sign/n1/1_2.png",
    "type": "1. ՆԱԽԱԶԳՈՒՇԱՑՆՈՂ ՆՇԱՆՆԵՐ"
  },
  {
    "title": "1.3.1. «Միագիծ երկաթուղի»",
    "description": "1.3.1. «Միագիծ երկաթուղի»",
    "imageUrl": "https://varord.am/images/sign/n1/1_3_1.png",
    "type": "1. ՆԱԽԱԶԳՈՒՇԱՑՆՈՂ ՆՇԱՆՆԵՐ"
  },
  {
    "title": "1.3.2. «Բազմագիծ երկաթուղի»",
    "description": "1.3.2. «Բազմագիծ երկաթուղի»",
    "imageUrl": "https://varord.am/images/sign/n1/1_3_2.png",
    "type": "1. ՆԱԽԱԶԳՈՒՇԱՑՆՈՂ ՆՇԱՆՆԵՐ"
  },
  {
    "title": "1.4.1. «Մոտեցում երկաթուղային գծանցին»",
    "description": "1.4.1. «Մոտեցում երկաթուղային գծանցին»",
    "imageUrl": "https://varord.am/images/sign/n1/1_4_1.png",
    "type": "1. ՆԱԽԱԶԳՈՒՇԱՑՆՈՂ ՆՇԱՆՆԵՐ"
  },
  {
    "title": "1.4.2. «Մոտեցում երկաթուղային գծանցին»",
    "description": "1.4.2. «Մոտեցում երկաթուղային գծանցին»",
    "imageUrl": "https://varord.am/images/sign/n1/1_4_2.png",
    "type": "1. ՆԱԽԱԶԳՈՒՇԱՑՆՈՂ ՆՇԱՆՆԵՐ"
  },
  {
    "title": "1.4.3. «Մոտեցում երկաթուղային գծանցին»",
    "description": "1.4.3. «Մոտեցում երկաթուղային գծանցին»",
    "imageUrl": "https://varord.am/images/sign/n1/1_4_3.png",
    "type": "1. ՆԱԽԱԶԳՈՒՇԱՑՆՈՂ ՆՇԱՆՆԵՐ"
  },
  {
    "title": "1.4.4. «Մոտեցում երկաթուղային գծանցին»",
    "description": "1.4.4. «Մոտեցում երկաթուղային գծանցին»",
    "imageUrl": "https://varord.am/images/sign/n1/1_4_4.png",
    "type": "1. ՆԱԽԱԶԳՈՒՇԱՑՆՈՂ ՆՇԱՆՆԵՐ"
  },
  {
    "title": "1.4.5. «Մոտեցում երկաթուղային գծանցին»",
    "description": "1.4.5. «Մոտեցում երկաթուղային գծանցին»",
    "imageUrl": "https://varord.am/images/sign/n1/1_4_5.png",
    "type": "1. ՆԱԽԱԶԳՈՒՇԱՑՆՈՂ ՆՇԱՆՆԵՐ"
  },
  {
    "title": "1.4.6. «Մոտեցում երկաթուղային գծանցին»",
    "description": "1.4.6. «Մոտեցում երկաթուղային գծանցին»",
    "imageUrl": "https://varord.am/images/sign/n1/1_4_6.png",
    "type": "1. ՆԱԽԱԶԳՈՒՇԱՑՆՈՂ ՆՇԱՆՆԵՐ"
  },
  {
    "title": "1.5. «Հատում տրամվայի գծի հետ»",
    "description": "1.5. «Հատում տրամվայի գծի հետ»",
    "imageUrl": "https://varord.am/images/sign/n1/1_5.png",
    "type": "1. ՆԱԽԱԶԳՈՒՇԱՑՆՈՂ ՆՇԱՆՆԵՐ"
  },
  {
    "title": "1.6. «Հավասարազոր ճանապարհների հատում»",
    "description": "1.6. «Հավասարազոր ճանապարհների հատում»",
    "imageUrl": "https://varord.am/images/sign/n1/1_6.png",
    "type": "1. ՆԱԽԱԶԳՈՒՇԱՑՆՈՂ ՆՇԱՆՆԵՐ"
  },
  {
    "title": "1.7. «Հատում շրջանաձև երթևեկության հետ»",
    "description": "1.7. «Հատում շրջանաձև երթևեկության հետ»",
    "imageUrl": "https://varord.am/images/sign/n1/1_7.png",
    "type": "1. ՆԱԽԱԶԳՈՒՇԱՑՆՈՂ ՆՇԱՆՆԵՐ"
  },
  {
    "title": "1.8. «Լուսացուցային կարգավորում»",
    "description": "1.8. «Լուսացուցային կարգավորում»",
    "imageUrl": "https://varord.am/images/sign/n1/1_8.png",
    "type": "1. ՆԱԽԱԶԳՈՒՇԱՑՆՈՂ ՆՇԱՆՆԵՐ"
  },
  {
    "title": "1.9. «Բացվող կամուրջ»",
    "description": "1.9. «Բացվող կամուրջ»",
    "imageUrl": "https://varord.am/images/sign/n1/1_9.png",
    "type": "1. ՆԱԽԱԶԳՈՒՇԱՑՆՈՂ ՆՇԱՆՆԵՐ"
  },
  {
    "title": "1.10. «Ելք դեպի առափ»",
    "description": "1.10. «Ելք դեպի առափ»",
    "imageUrl": "https://varord.am/images/sign/n1/1_10.png",
    "type": "1. ՆԱԽԱԶԳՈՒՇԱՑՆՈՂ ՆՇԱՆՆԵՐ"
  },
  {
    "title": "1.11.2. «Վտանգավոր շրջադարձ»",
    "description": "1.11.2. «Վտանգավոր շրջադարձ»",
    "imageUrl": "https://varord.am/images/sign/n1/1_11_2.png",
    "type": "1. ՆԱԽԱԶԳՈՒՇԱՑՆՈՂ ՆՇԱՆՆԵՐ"
  },
  {
    "title": "1.12.1. «Վտանգավոր շրջադարձեր»",
    "description": "1.12.1. «Վտանգավոր շրջադարձեր»",
    "imageUrl": "https://varord.am/images/sign/n1/1_12_1.png",
    "type": "1. ՆԱԽԱԶԳՈՒՇԱՑՆՈՂ ՆՇԱՆՆԵՐ"
  },
  {
    "title": "1.12.2. «Վտանգավոր շրջադարձեր»",
    "description": "1.12.2. «Վտանգավոր շրջադարձեր»",
    "imageUrl": "https://varord.am/images/sign/n1/1_12_2.png",
    "type": "1. ՆԱԽԱԶԳՈՒՇԱՑՆՈՂ ՆՇԱՆՆԵՐ"
  },
  {
    "title": "1.13. «Կտրուկ վայրէջք»",
    "description": "1.13. «Կտրուկ վայրէջք»",
    "imageUrl": "https://varord.am/images/sign/n1/1_13.png",
    "type": "1. ՆԱԽԱԶԳՈՒՇԱՑՆՈՂ ՆՇԱՆՆԵՐ"
  },
  {
    "title": "1.14. «Կտրուկ վերելք»",
    "description": "1.14. «Կտրուկ վերելք»",
    "imageUrl": "https://varord.am/images/sign/n1/1_14.png",
    "type": "1. ՆԱԽԱԶԳՈՒՇԱՑՆՈՂ ՆՇԱՆՆԵՐ"
  },
  {
    "title": "1.15. «Սայթաքուն ճանապարհ»",
    "description": "1.15. «Սայթաքուն ճանապարհ»",
    "imageUrl": "https://varord.am/images/sign/n1/1_15.png",
    "type": "1. ՆԱԽԱԶԳՈՒՇԱՑՆՈՂ ՆՇԱՆՆԵՐ"
  },
  {
    "title": "1.16. «Անհարթ ճանապարհ»",
    "description": "1.16. «Անհարթ ճանապարհ»",
    "imageUrl": "https://varord.am/images/sign/n1/1_16.png",
    "type": "1. ՆԱԽԱԶԳՈՒՇԱՑՆՈՂ ՆՇԱՆՆԵՐ"
  },
  {
    "title": "1.17. «Արհեստական անհարթություն»",
    "description": "1.17. «Արհեստական անհարթություն»",
    "imageUrl": "https://varord.am/images/sign/n1/1_17.png",
    "type": "1. ՆԱԽԱԶԳՈՒՇԱՑՆՈՂ ՆՇԱՆՆԵՐ"
  },
  {
    "title": "1.18. «Խճի արտանետում»",
    "description": "1.18. «Խճի արտանետում»",
    "imageUrl": "https://varord.am/images/sign/n1/1_18.png",
    "type": "1. ՆԱԽԱԶԳՈՒՇԱՑՆՈՂ ՆՇԱՆՆԵՐ"
  },
  {
    "title": "1.19. «Վտանգավոր կողնակ»",
    "description": "1.19. «Վտանգավոր կողնակ»",
    "imageUrl": "https://varord.am/images/sign/n1/1_19.png",
    "type": "1. ՆԱԽԱԶԳՈՒՇԱՑՆՈՂ ՆՇԱՆՆԵՐ"
  },
  {
    "title": "1.20.1. «Ճանապարհի նեղացում»",
    "description": "1.20.1. «Ճանապարհի նեղացում»",
    "imageUrl": "https://varord.am/images/sign/n1/1_20_1.png",
    "type": "1. ՆԱԽԱԶԳՈՒՇԱՑՆՈՂ ՆՇԱՆՆԵՐ"
  },
  {
    "title": "1.20.2. «Ճանապարհի նեղացում»",
    "description": "1.20.2. «Ճանապարհի նեղացում»",
    "imageUrl": "https://varord.am/images/sign/n1/1_20_2.png",
    "type": "1. ՆԱԽԱԶԳՈՒՇԱՑՆՈՂ ՆՇԱՆՆԵՐ"
  },
  {
    "title": "1.20.3. «Ճանապարհի նեղացում»",
    "description": "1.20.3. «Ճանապարհի նեղացում»",
    "imageUrl": "https://varord.am/images/sign/n1/1_20_3.png",
    "type": "1. ՆԱԽԱԶԳՈՒՇԱՑՆՈՂ ՆՇԱՆՆԵՐ"
  },
  {
    "title": "1.21. «Երկկողմ երթևեկություն»",
    "description": "1.21. «Երկկողմ երթևեկություն»",
    "imageUrl": "https://varord.am/images/sign/n1/1_21.png",
    "type": "1. ՆԱԽԱԶԳՈՒՇԱՑՆՈՂ ՆՇԱՆՆԵՐ"
  },
  {
    "title": "1.22. «Հետիոտնային անցում»",
    "description": "1.22. «Հետիոտնային անցում»",
    "imageUrl": "https://varord.am/images/sign/n1/1_22.png",
    "type": "1. ՆԱԽԱԶԳՈՒՇԱՑՆՈՂ ՆՇԱՆՆԵՐ"
  },
  {
    "title": "1.23. «Երեխաներ»",
    "description": "1.23. «Երեխաներ»",
    "imageUrl": "https://varord.am/images/sign/n1/1_23.png",
    "type": "1. ՆԱԽԱԶԳՈՒՇԱՑՆՈՂ ՆՇԱՆՆԵՐ"
  },
  {
    "title": "1.24. «Հատում հեծանվային արահետի հետ»",
    "description": "1.24. «Հատում հեծանվային արահետի հետ»",
    "imageUrl": "https://varord.am/images/sign/n1/1_24.png",
    "type": "1. ՆԱԽԱԶԳՈՒՇԱՑՆՈՂ ՆՇԱՆՆԵՐ"
  },
  {
    "title": "1.25. «Ճանապարհային աշխատանքներ»",
    "description": "1.25. «Ճանապարհային աշխատանքներ»",
    "imageUrl": "https://varord.am/images/sign/n1/1_25.png",
    "type": "1. ՆԱԽԱԶԳՈՒՇԱՑՆՈՂ ՆՇԱՆՆԵՐ"
  },
  {
    "title": "1.26. «Անասունների քշում»",
    "description": "1.26. «Անասունների քշում»",
    "imageUrl": "https://varord.am/images/sign/n1/1_26.png",
    "type": "1. ՆԱԽԱԶԳՈՒՇԱՑՆՈՂ ՆՇԱՆՆԵՐ"
  },
  {
    "title": "1.27. «Վայրի կենդանիներ»",
    "description": "1.27. «Վայրի կենդանիներ»",
    "imageUrl": "https://varord.am/images/sign/n1/1_27.png",
    "type": "1. ՆԱԽԱԶԳՈՒՇԱՑՆՈՂ ՆՇԱՆՆԵՐ"
  },
  {
    "title": "1.28. «Քարերի անկում»",
    "description": "1.28. «Քարերի անկում»",
    "imageUrl": "https://varord.am/images/sign/n1/1_28.png",
    "type": "1. ՆԱԽԱԶԳՈՒՇԱՑՆՈՂ ՆՇԱՆՆԵՐ"
  },
  {
    "title": "1.29. «Կողային քամի»",
    "description": "1.29. «Կողային քամի»",
    "imageUrl": "https://varord.am/images/sign/n1/1_29.png",
    "type": "1. ՆԱԽԱԶԳՈՒՇԱՑՆՈՂ ՆՇԱՆՆԵՐ"
  },
  {
    "title": "1.30. «Ցածրաթռիչք ինքնաթիռներ»",
    "description": "1.30. «Ցածրաթռիչք ինքնաթիռներ»",
    "imageUrl": "https://varord.am/images/sign/n1/1_30.png",
    "type": "1. ՆԱԽԱԶԳՈՒՇԱՑՆՈՂ ՆՇԱՆՆԵՐ"
  },
  {
    "title": "1.31. «Թունել»",
    "description": "1.31. «Թունել»",
    "imageUrl": "https://varord.am/images/sign/n1/1_31.png",
    "type": "1. ՆԱԽԱԶԳՈՒՇԱՑՆՈՂ ՆՇԱՆՆԵՐ"
  },
  {
    "title": "1.32. «Խցանում»",
    "description": "1.32. «Խցանում»",
    "imageUrl": "https://varord.am/images/sign/n1/1_32.png",
    "type": "1. ՆԱԽԱԶԳՈՒՇԱՑՆՈՂ ՆՇԱՆՆԵՐ"
  },
  {
    "title": "1.33. «Այլ վտանգներ»",
    "description": "1.33. «Այլ վտանգներ»",
    "imageUrl": "https://varord.am/images/sign/n1/1_33.png",
    "type": "1. ՆԱԽԱԶԳՈՒՇԱՑՆՈՂ ՆՇԱՆՆԵՐ"
  },
  {
    "title": "1.34.1«Շրջադարձի ուղղություն»",
    "description": "1.34.1«Շրջադարձի ուղղություն»",
    "imageUrl": "https://varord.am/images/sign/n1/1_34_1.png",
    "type": "1. ՆԱԽԱԶԳՈՒՇԱՑՆՈՂ ՆՇԱՆՆԵՐ"
  },
  {
    "title": "1.34.2«Շրջադարձի ուղղություն»",
    "description": "1.34.2«Շրջադարձի ուղղություն»",
    "imageUrl": "https://varord.am/images/sign/n1/1_34_2.png",
    "type": "1. ՆԱԽԱԶԳՈՒՇԱՑՆՈՂ ՆՇԱՆՆԵՐ"
  },
  {
    "title": "1.34.3«Շրջադարձի ուղղություն»",
    "description": "1.34.3«Շրջադարձի ուղղություն»",
    "imageUrl": "https://varord.am/images/sign/n1/1_34_3.png",
    "type": "1. ՆԱԽԱԶԳՈՒՇԱՑՆՈՂ ՆՇԱՆՆԵՐ"
  },
  {
    "title": "1.35. «Խաչմերուկի տարածք»",
    "description": "1.35. «Խաչմերուկի տարածք»",
    "imageUrl": "https://varord.am/images/sign/n1/1_35.png",
    "type": "1. ՆԱԽԱԶԳՈՒՇԱՑՆՈՂ ՆՇԱՆՆԵՐ"
  },
  {
    "title": "2.1. «Գլխավոր ճանապարհ»",
    "description": "2.1. «Գլխավոր ճանապարհ»",
    "imageUrl": "https://varord.am/images/sign/n2/2_1.png",
    "type": "2. ԱՌԱՎԵԼՈՒԹՅԱՆ ՆՇԱՆՆԵՐ"
  },
  {
    "title": "2.2. «Գլխավոր ճանապարհի վերջ»",
    "description": "2.2. «Գլխավոր ճանապարհի վերջ»",
    "imageUrl": "https://varord.am/images/sign/n2/2_2.png",
    "type": "2. ԱՌԱՎԵԼՈՒԹՅԱՆ ՆՇԱՆՆԵՐ"
  },
  {
    "title": "2.3.1. «Հատում երկրորդական ճանապարհի հետ»",
    "description": "2.3.1. «Հատում երկրորդական ճանապարհի հետ»",
    "imageUrl": "https://varord.am/images/sign/n2/2_3_1.png",
    "type": "2. ԱՌԱՎԵԼՈՒԹՅԱՆ ՆՇԱՆՆԵՐ"
  },
  {
    "title": "2.3.2. «Երկրորդական ճանապարհի հարում»",
    "description": "2.3.2. «Երկրորդական ճանապարհի հարում»",
    "imageUrl": "https://varord.am/images/sign/n2/2_3_2.png",
    "type": "2. ԱՌԱՎԵԼՈՒԹՅԱՆ ՆՇԱՆՆԵՐ"
  },
  {
    "title": "2.3.3. «Երկրորդական ճանապարհի հարում»",
    "description": "2.3.3. «Երկրորդական ճանապարհի հարում»",
    "imageUrl": "https://varord.am/images/sign/n2/2_3_3.png",
    "type": "2. ԱՌԱՎԵԼՈՒԹՅԱՆ ՆՇԱՆՆԵՐ"
  },
  {
    "title": "2.3.4. «Երկրորդական ճանապարհի հարում»",
    "description": "2.3.4. «Երկրորդական ճանապարհի հարում»",
    "imageUrl": "https://varord.am/images/sign/n2/2_3_4.png",
    "type": "2. ԱՌԱՎԵԼՈՒԹՅԱՆ ՆՇԱՆՆԵՐ"
  },
  {
    "title": "2.3.5. «Երկրորդական ճանապարհի հարում»",
    "description": "2.3.5. «Երկրորդական ճանապարհի հարում»",
    "imageUrl": "https://varord.am/images/sign/n2/2_3_5.png",
    "type": "2. ԱՌԱՎԵԼՈՒԹՅԱՆ ՆՇԱՆՆԵՐ"
  },
  {
    "title": "2.3.6. «Երկրորդական ճանապարհի հարում»",
    "description": "2.3.6. «Երկրորդական ճանապարհի հարում»",
    "imageUrl": "https://varord.am/images/sign/n2/2_3_6.png",
    "type": "2. ԱՌԱՎԵԼՈՒԹՅԱՆ ՆՇԱՆՆԵՐ"
  },
  {
    "title": "2.3.7. «Երկրորդական ճանապարհի հարում»",
    "description": "2.3.7. «Երկրորդական ճանապարհի հարում»",
    "imageUrl": "https://varord.am/images/sign/n2/2_3_7.png",
    "type": "2. ԱՌԱՎԵԼՈՒԹՅԱՆ ՆՇԱՆՆԵՐ"
  },
  {
    "title": "2.4. «Զիջեք ճանապարհը»",
    "description": "2.4. «Զիջեք ճանապարհը»",
    "imageUrl": "https://varord.am/images/sign/n2/2_4.png",
    "type": "2. ԱՌԱՎԵԼՈՒԹՅԱՆ ՆՇԱՆՆԵՐ"
  },
  {
    "title": "2.5. «Երթևեկությունն առանց կանգառի արգելվում է»",
    "description": "2.5. «Երթևեկությունն առանց կանգառի արգելվում է»",
    "imageUrl": "https://varord.am/images/sign/n2/2_5.png",
    "type": "2. ԱՌԱՎԵԼՈՒԹՅԱՆ ՆՇԱՆՆԵՐ"
  },
  {
    "title": "2.6. «Հանդիպակաց երթևեկության առավելություն»",
    "description": "2.6. «Հանդիպակաց երթևեկության առավելություն»",
    "imageUrl": "https://varord.am/images/sign/n2/2_6.png",
    "type": "2. ԱՌԱՎԵԼՈՒԹՅԱՆ ՆՇԱՆՆԵՐ"
  },
  {
    "title": "2.7. «Առավելություն հանդիպակաց երթևեկության նկատմամբ»",
    "description": "2.7. «Առավելություն հանդիպակաց երթևեկության նկատմամբ»",
    "imageUrl": "https://varord.am/images/sign/n2/2_7.png",
    "type": "2. ԱՌԱՎԵԼՈՒԹՅԱՆ ՆՇԱՆՆԵՐ"
  },
  {
    "title": "3.1. «Մուտքն արգելվում է»",
    "description": "3.1. «Մուտքն արգելվում է»",
    "imageUrl": "https://varord.am/images/sign/n3/3_1.png",
    "type": "3. ԱՐԳԵԼՈՂ ՆՇԱՆՆԵՐ"
  },
  {
    "title": "3.2. «Երթևեկությունն արգելվում է»",
    "description": "3.2. «Երթևեկությունն արգելվում է»",
    "imageUrl": "https://varord.am/images/sign/n3/3_2.png",
    "type": "3. ԱՐԳԵԼՈՂ ՆՇԱՆՆԵՐ"
  },
  {
    "title": "3.3. «Մեխանիկական տրանսպորտային միջոցների երթևեկությունն արգելվում է»",
    "description": "3.3. «Մեխանիկական տրանսպորտային միջոցների երթևեկությունն արգելվում է»",
    "imageUrl": "https://varord.am/images/sign/n3/3_3.png",
    "type": "3. ԱՐԳԵԼՈՂ ՆՇԱՆՆԵՐ"
  },
  {
    "title": "3.4. «Բեռնատար ավտոմոբիլների երթևեկությունն արգելվում է»",
    "description": "3.4. «Բեռնատար ավտոմոբիլների երթևեկությունն արգելվում է»",
    "imageUrl": "https://varord.am/images/sign/n3/3_4.png",
    "type": "3. ԱՐԳԵԼՈՂ ՆՇԱՆՆԵՐ"
  },
  {
    "title": "3.5. «Մոտոցիկլների երթևեկությունն արգելվում է»",
    "description": "3.5. «Մոտոցիկլների երթևեկությունն արգելվում է»",
    "imageUrl": "https://varord.am/images/sign/n3/3_5.png",
    "type": "3. ԱՐԳԵԼՈՂ ՆՇԱՆՆԵՐ"
  },
  {
    "title": "3.6. «Տրակտորների երթևեկությունն արգելվում է»",
    "description": "3.6. «Տրակտորների երթևեկությունն արգելվում է»",
    "imageUrl": "https://varord.am/images/sign/n3/3_6.png",
    "type": "3. ԱՐԳԵԼՈՂ ՆՇԱՆՆԵՐ"
  },
  {
    "title": "3.7. «Կցորդով երթևեկությունն արգելվում է»",
    "description": "3.7. «Կցորդով երթևեկությունն արգելվում է»",
    "imageUrl": "https://varord.am/images/sign/n3/3_7.png",
    "type": "3. ԱՐԳԵԼՈՂ ՆՇԱՆՆԵՐ"
  },
  {
    "title": "3.8. «Լծասայլերի երթևեկությունն արգելվում է»",
    "description": "3.8. «Լծասայլերի երթևեկությունն արգելվում է»",
    "imageUrl": "https://varord.am/images/sign/n3/3_8.png",
    "type": "3. ԱՐԳԵԼՈՂ ՆՇԱՆՆԵՐ"
  },
  {
    "title": "3.9. «Հեծանիվներով երթևեկությունն արգելվում է»",
    "description": "3.9. «Հեծանիվներով երթևեկությունն արգելվում է»",
    "imageUrl": "https://varord.am/images/sign/n3/3_9.png",
    "type": "3. ԱՐԳԵԼՈՂ ՆՇԱՆՆԵՐ"
  },
  {
    "title": "3.10. «Հետիոտների տեղաշարժն արգելվում է»",
    "description": "3.10. «Հետիոտների տեղաշարժն արգելվում է»",
    "imageUrl": "https://varord.am/images/sign/n3/3_10.png",
    "type": "3. ԱՐԳԵԼՈՂ ՆՇԱՆՆԵՐ"
  },
  {
    "title": "3.11. «Զանգվածի սահմանափակում»",
    "description": "3.11. «Զանգվածի սահմանափակում»",
    "imageUrl": "https://varord.am/images/sign/n3/3_11.png",
    "type": "3. ԱՐԳԵԼՈՂ ՆՇԱՆՆԵՐ"
  },
  {
    "title": "3.12. «Սռնու վրա բեռնվածության սահմանափակում»",
    "description": "3.12. «Սռնու վրա բեռնվածության սահմանափակում»",
    "imageUrl": "https://varord.am/images/sign/n3/3_12.png",
    "type": "3. ԱՐԳԵԼՈՂ ՆՇԱՆՆԵՐ"
  },
  {
    "title": "3.13. «Բարձրության սահմանափակում»",
    "description": "3.13. «Բարձրության սահմանափակում»",
    "imageUrl": "https://varord.am/images/sign/n3/3_13.png",
    "type": "3. ԱՐԳԵԼՈՂ ՆՇԱՆՆԵՐ"
  },
  {
    "title": "3.14. «Լայնության սահմանափակում»",
    "description": "3.14. «Լայնության սահմանափակում»",
    "imageUrl": "https://varord.am/images/sign/n3/3_14.png",
    "type": "3. ԱՐԳԵԼՈՂ ՆՇԱՆՆԵՐ"
  },
  {
    "title": "3.15. «Երկարության սահմանափակում»",
    "description": "3.15. «Երկարության սահմանափակում»",
    "imageUrl": "https://varord.am/images/sign/n3/3_15.png",
    "type": "3. ԱՐԳԵԼՈՂ ՆՇԱՆՆԵՐ"
  },
  {
    "title": "3.16. «Նվազագույն միջտարածության սահմանափակում»",
    "description": "3.16. «Նվազագույն միջտարածության սահմանափակում»",
    "imageUrl": "https://varord.am/images/sign/n3/3_16.png",
    "type": "3. ԱՐԳԵԼՈՂ ՆՇԱՆՆԵՐ"
  },
  {
    "title": "3.17.1. «Մաքսային կետ»",
    "description": "3.17.1. «Մաքսային կետ»",
    "imageUrl": "https://varord.am/images/sign/n3/3_17_1.png",
    "type": "3. ԱՐԳԵԼՈՂ ՆՇԱՆՆԵՐ"
  },
  {
    "title": "3.17.2. «Վտանգ»",
    "description": "3.17.2. «Վտանգ»",
    "imageUrl": "https://varord.am/images/sign/n3/3_17_2.png",
    "type": "3. ԱՐԳԵԼՈՂ ՆՇԱՆՆԵՐ"
  },
  {
    "title": "3.17.3. «Հսկիչ կետ»",
    "description": "3.17.3. «Հսկիչ կետ»",
    "imageUrl": "https://varord.am/images/sign/n3/3_17_3.png",
    "type": "3. ԱՐԳԵԼՈՂ ՆՇԱՆՆԵՐ"
  },
  {
    "title": "3.18.1. «Աջ շրջադարձն արգելվում է»",
    "description": "3.18.1. «Աջ շրջադարձն արգելվում է»",
    "imageUrl": "https://varord.am/images/sign/n3/3_18_1.png",
    "type": "3. ԱՐԳԵԼՈՂ ՆՇԱՆՆԵՐ"
  },
  {
    "title": "3.18.2. «Ձախ շրջադարձն արգելվում է»",
    "description": "3.18.2. «Ձախ շրջադարձն արգելվում է»",
    "imageUrl": "https://varord.am/images/sign/n3/3_18_2.png",
    "type": "3. ԱՐԳԵԼՈՂ ՆՇԱՆՆԵՐ"
  },
  {
    "title": "3.19. «Հետադարձն արգելվում է»",
    "description": "3.19. «Հետադարձն արգելվում է»",
    "imageUrl": "https://varord.am/images/sign/n3/3_19.png",
    "type": "3. ԱՐԳԵԼՈՂ ՆՇԱՆՆԵՐ"
  },
  {
    "title": "3.20. «Վազանցն արգելվում է»",
    "description": "3.20. «Վազանցն արգելվում է»",
    "imageUrl": "https://varord.am/images/sign/n3/3_20.png",
    "type": "3. ԱՐԳԵԼՈՂ ՆՇԱՆՆԵՐ"
  },
  {
    "title": "3.21. «Վազանցի արգելման գոտու վերջ»",
    "description": "3.21. «Վազանցի արգելման գոտու վերջ»",
    "imageUrl": "https://varord.am/images/sign/n3/3_21.png",
    "type": "3. ԱՐԳԵԼՈՂ ՆՇԱՆՆԵՐ"
  },
  {
    "title": "3.22. «Բեռնատար ավտոմոբիլներով վազանցն արգելվում է»",
    "description": "3.22. «Բեռնատար ավտոմոբիլներով վազանցն արգելվում է»",
    "imageUrl": "https://varord.am/images/sign/n3/3_22.png",
    "type": "3. ԱՐԳԵԼՈՂ ՆՇԱՆՆԵՐ"
  },
  {
    "title": "3.23. «Բեռնատար ավտոմոբիլներով վազանցի արգելման գոտու վերջ»",
    "description": "3.23. «Բեռնատար ավտոմոբիլներով վազանցի արգելման գոտու վերջ»",
    "imageUrl": "https://varord.am/images/sign/n3/3_23.png",
    "type": "3. ԱՐԳԵԼՈՂ ՆՇԱՆՆԵՐ"
  },
  {
    "title": "3.24. «Առավելագույն արագության սահմանափակում»",
    "description": "3.24. «Առավելագույն արագության սահմանափակում»",
    "imageUrl": "https://varord.am/images/sign/n3/3_24.png",
    "type": "3. ԱՐԳԵԼՈՂ ՆՇԱՆՆԵՐ"
  },
  {
    "title": "3.25. «Առավելագույն արագության սահմանափակման գոտու վերջ»",
    "description": "3.25. «Առավելագույն արագության սահմանափակման գոտու վերջ»",
    "imageUrl": "https://varord.am/images/sign/n3/3_25.png",
    "type": "3. ԱՐԳԵԼՈՂ ՆՇԱՆՆԵՐ"
  },
  {
    "title": "3.26. «Ձայնային ազդանշան տալն արգելվում է»",
    "description": "3.26. «Ձայնային ազդանշան տալն արգելվում է»",
    "imageUrl": "https://varord.am/images/sign/n3/3_26.png",
    "type": "3. ԱՐԳԵԼՈՂ ՆՇԱՆՆԵՐ"
  },
  {
    "title": "3.27. «Կանգառն արգելվում է»",
    "description": "3.27. «Կանգառն արգելվում է»",
    "imageUrl": "https://varord.am/images/sign/n3/3_27.png",
    "type": "3. ԱՐԳԵԼՈՂ ՆՇԱՆՆԵՐ"
  },
  {
    "title": "3.28. «Կայանելն արգելվում է»",
    "description": "3.28. «Կայանելն արգելվում է»",
    "imageUrl": "https://varord.am/images/sign/n3/3_28.png",
    "type": "3. ԱՐԳԵԼՈՂ ՆՇԱՆՆԵՐ"
  },
  {
    "title": "3.29. «Կայանելն արգելվում է ամսվա կենտ օրերին»",
    "description": "3.29. «Կայանելն արգելվում է ամսվա կենտ օրերին»",
    "imageUrl": "https://varord.am/images/sign/n3/3_29.png",
    "type": "3. ԱՐԳԵԼՈՂ ՆՇԱՆՆԵՐ"
  },
  {
    "title": "3.30. «Կայանելն արգելվում է ամսվա զույգ օրերին»",
    "description": "3.30. «Կայանելն արգելվում է ամսվա զույգ օրերին»",
    "imageUrl": "https://varord.am/images/sign/n3/3_30.png",
    "type": "3. ԱՐԳԵԼՈՂ ՆՇԱՆՆԵՐ"
  },
  {
    "title": "3.31. «Բոլոր սահմանափակումների գոտու վերջ»",
    "description": "3.31. «Բոլոր սահմանափակումների գոտու վերջ»",
    "imageUrl": "https://varord.am/images/sign/n3/3_31.png",
    "type": "3. ԱՐԳԵԼՈՂ ՆՇԱՆՆԵՐ"
  },
  {
    "title": "3.32. «Վտանգավոր բեռներով տրանսպորտային միջոցների երթևեկությունն արգելվում է»",
    "description": "3.32. «Վտանգավոր բեռներով տրանսպորտային միջոցների երթևեկությունն արգելվում է»",
    "imageUrl": "https://varord.am/images/sign/n3/3_32.png",
    "type": "3. ԱՐԳԵԼՈՂ ՆՇԱՆՆԵՐ"
  },
  {
    "title": "3.33. «Պայթուցիկ և դյուրավառ բեռներով տրանսպորտային միջոցների երթևեկությունն արգելվում է»",
    "description": "3.33. «Պայթուցիկ և դյուրավառ բեռներով տրանսպորտային միջոցների երթևեկությունն արգելվում է»",
    "imageUrl": "https://varord.am/images/sign/n3/3_33.png",
    "type": "3. ԱՐԳԵԼՈՂ ՆՇԱՆՆԵՐ"
  },
  {
    "title": "4.1.1. «Երթևեկությունն ուղիղ»",
    "description": "4.1.1. «Երթևեկությունն ուղիղ»",
    "imageUrl": "https://varord.am/images/sign/n4/4_1_1.png",
    "type": "4. ԹԵԼԱԴՐՈՂ ՆՇԱՆՆԵՐ"
  },
  {
    "title": "4.1.2. «Երթևեկությունը դեպի աջ»",
    "description": "4.1.2. «Երթևեկությունը դեպի աջ»",
    "imageUrl": "https://varord.am/images/sign/n4/4_1_2.png",
    "type": "4. ԹԵԼԱԴՐՈՂ ՆՇԱՆՆԵՐ"
  },
  {
    "title": "4.1.3. «Երթևեկությունը դեպի ձախ»",
    "description": "4.1.3. «Երթևեկությունը դեպի ձախ»",
    "imageUrl": "https://varord.am/images/sign/n4/4_1_3.png",
    "type": "4. ԹԵԼԱԴՐՈՂ ՆՇԱՆՆԵՐ"
  },
  {
    "title": "4.1.4. «Երթևեկությունն ուղիղ կամ դեպի աջ»",
    "description": "4.1.4. «Երթևեկությունն ուղիղ կամ դեպի աջ»",
    "imageUrl": "https://varord.am/images/sign/n4/4_1_4.png",
    "type": "4. ԹԵԼԱԴՐՈՂ ՆՇԱՆՆԵՐ"
  },
  {
    "title": "4.1.5. «Երթևեկությունն ուղիղ կամ դեպի ձախ»",
    "description": "4.1.5. «Երթևեկությունն ուղիղ կամ դեպի ձախ»",
    "imageUrl": "https://varord.am/images/sign/n4/4_1_5.png",
    "type": "4. ԹԵԼԱԴՐՈՂ ՆՇԱՆՆԵՐ"
  },
  {
    "title": "4.1.6. «Երթևեկությունը դեպի աջ կամ դեպի ձախ»",
    "description": "4.1.6. «Երթևեկությունը դեպի աջ կամ դեպի ձախ»",
    "imageUrl": "https://varord.am/images/sign/n4/4_1_6.png",
    "type": "4. ԹԵԼԱԴՐՈՂ ՆՇԱՆՆԵՐ"
  },
  {
    "title": "4.2.1. «Արգելքի շրջանցումն աջից»",
    "description": "4.2.1. «Արգելքի շրջանցումն աջից»",
    "imageUrl": "https://varord.am/images/sign/n4/4_2_1.png",
    "type": "4. ԹԵԼԱԴՐՈՂ ՆՇԱՆՆԵՐ"
  },
  {
    "title": "4.2.2. «Արգելքի շրջանցումը ձախից»",
    "description": "4.2.2. «Արգելքի շրջանցումը ձախից»",
    "imageUrl": "https://varord.am/images/sign/n4/4_2_2.png",
    "type": "4. ԹԵԼԱԴՐՈՂ ՆՇԱՆՆԵՐ"
  },
  {
    "title": "4.2.3. «Արգելքի շրջանցումն աջից կամ ձախից»",
    "description": "4.2.3. «Արգելքի շրջանցումն աջից կամ ձախից»",
    "imageUrl": "https://varord.am/images/sign/n4/4_2_3.png",
    "type": "4. ԹԵԼԱԴՐՈՂ ՆՇԱՆՆԵՐ"
  },
  {
    "title": "4.3. «Շրջանաձև երթևեկություն»",
    "description": "4.3. «Շրջանաձև երթևեկություն»",
    "imageUrl": "https://varord.am/images/sign/n4/4_3.png",
    "type": "4. ԹԵԼԱԴՐՈՂ ՆՇԱՆՆԵՐ"
  },
  {
    "title": "4.4.1 «Հեծանվային արահետ»",
    "description": "4.4.1 «Հեծանվային արահետ»",
    "imageUrl": "https://varord.am/images/sign/n4/4_4_1.png",
    "type": "4. ԹԵԼԱԴՐՈՂ ՆՇԱՆՆԵՐ"
  },
  {
    "title": "4.4.2 «Հեծանվային արահետի վերջ»",
    "description": "4.4.2 «Հեծանվային արահետի վերջ»",
    "imageUrl": "https://varord.am/images/sign/n4/4_4_2.png",
    "type": "4. ԹԵԼԱԴՐՈՂ ՆՇԱՆՆԵՐ"
  },
  {
    "title": "4.5.1 «Հետիոտնային արահետ»",
    "description": "4.5.1 «Հետիոտնային արահետ»",
    "imageUrl": "https://varord.am/images/sign/n4/4_5_1.png",
    "type": "4. ԹԵԼԱԴՐՈՂ ՆՇԱՆՆԵՐ"
  },
  {
    "title": "4.5.2 «Համատեղ երթևեկությամբ հետիոտնային և հեծանվային արահետ »",
    "description": "4.5.2 «Համատեղ երթևեկությամբ հետիոտնային և հեծանվային արահետ »",
    "imageUrl": "https://varord.am/images/sign/n4/4_5_2.png",
    "type": "4. ԹԵԼԱԴՐՈՂ ՆՇԱՆՆԵՐ"
  },
  {
    "title": "4.5.3 «Համատեղ երթևեկությամբ հետիոտնային և հեծանվային արահետի վերջ»",
    "description": "4.5.3 «Համատեղ երթևեկությամբ հետիոտնային և հեծանվային արահետի վերջ»",
    "imageUrl": "https://varord.am/images/sign/n4/4_5_3.png",
    "type": "4. ԹԵԼԱԴՐՈՂ ՆՇԱՆՆԵՐ"
  },
  {
    "title": "4.5.4 «Տարանջատված երթևեկությամբ հետիոտնային և հեծանվային արահետ»",
    "description": "4.5.4 «Տարանջատված երթևեկությամբ հետիոտնային և հեծանվային արահետ»",
    "imageUrl": "https://varord.am/images/sign/n4/4_5_4.png",
    "type": "4. ԹԵԼԱԴՐՈՂ ՆՇԱՆՆԵՐ"
  },
  {
    "title": "4.5.5. «Տարանջատված երթևեկությամբ հետիոտնային և հեծանվային արահետ»",
    "description": "4.5.5. «Տարանջատված երթևեկությամբ հետիոտնային և հեծանվային արահետ»",
    "imageUrl": "https://varord.am/images/sign/n4/4_5_5.png",
    "type": "4. ԹԵԼԱԴՐՈՂ ՆՇԱՆՆԵՐ"
  },
  {
    "title": "4.5.6 «Տարանջատված երթևեկությամբ հետիոտնային և հեծանվային արահետի վերջ»",
    "description": "4.5.6 «Տարանջատված երթևեկությամբ հետիոտնային և հեծանվային արահետի վերջ»",
    "imageUrl": "https://varord.am/images/sign/n4/4_5_6.png",
    "type": "4. ԹԵԼԱԴՐՈՂ ՆՇԱՆՆԵՐ"
  },
  {
    "title": "4.5.7. «Տարանջատված երթևեկությամբ հետիոտնային և հեծանվային արահետի վերջ»",
    "description": "4.5.7. «Տարանջատված երթևեկությամբ հետիոտնային և հեծանվային արահետի վերջ»",
    "imageUrl": "https://varord.am/images/sign/n4/4_5_7.png",
    "type": "4. ԹԵԼԱԴՐՈՂ ՆՇԱՆՆԵՐ"
  },
  {
    "title": "4.6. «Նվազագույն արագության սահմանափակում»",
    "description": "4.6. «Նվազագույն արագության սահմանափակում»",
    "imageUrl": "https://varord.am/images/sign/n4/4_6.png",
    "type": "4. ԹԵԼԱԴՐՈՂ ՆՇԱՆՆԵՐ"
  },
  {
    "title": "4.7. «Նվազագույն արագության սահմանափակման գոտու վերջ»",
    "description": "4.7. «Նվազագույն արագության սահմանափակման գոտու վերջ»",
    "imageUrl": "https://varord.am/images/sign/n4/4_7.png",
    "type": "4. ԹԵԼԱԴՐՈՂ ՆՇԱՆՆԵՐ"
  },
  {
    "title": "4.8.1 «Վտանգավոր բեռներով տրանսպորտային միջոցների երթևեկության ուղղություն»",
    "description": "4.8.1 «Վտանգավոր բեռներով տրանսպորտային միջոցների երթևեկության ուղղություն»",
    "imageUrl": "https://varord.am/images/sign/n4/4_8_1.png",
    "type": "4. ԹԵԼԱԴՐՈՂ ՆՇԱՆՆԵՐ"
  },
  {
    "title": "4.8.2 «Վտանգավոր բեռներով տրանսպորտային միջոցների երթևեկության ուղղություն»",
    "description": "4.8.2 «Վտանգավոր բեռներով տրանսպորտային միջոցների երթևեկության ուղղություն»",
    "imageUrl": "https://varord.am/images/sign/n4/4_8_2.png",
    "type": "4. ԹԵԼԱԴՐՈՂ ՆՇԱՆՆԵՐ"
  },
  {
    "title": "4.8.3 «Վտանգավոր բեռներով տրանսպորտային միջոցների երթևեկության ուղղություն»",
    "description": "4.8.3 «Վտանգավոր բեռներով տրանսպորտային միջոցների երթևեկության ուղղություն»",
    "imageUrl": "https://varord.am/images/sign/n4/4_8_3.png",
    "type": "4. ԹԵԼԱԴՐՈՂ ՆՇԱՆՆԵՐ"
  },
  {
    "title": "5.1. «Ավտոմայրուղի»",
    "description": "5.1. «Ավտոմայրուղի»",
    "imageUrl": "https://varord.am/images/sign/n5/5_1.png",
    "type": "5. ՀԱՏՈՒԿ ԹԵԼԱԴՐԱՆՔԻ ՆՇԱՆՆԵՐ"
  },
  {
    "title": "5.2. «Ավտոմայրուղու վերջ»",
    "description": "5.2. «Ավտոմայրուղու վերջ»",
    "imageUrl": "https://varord.am/images/sign/n5/5_2.png",
    "type": "5. ՀԱՏՈՒԿ ԹԵԼԱԴՐԱՆՔԻ ՆՇԱՆՆԵՐ"
  },
  {
    "title": "5.3. «Ճանապարհ ավտոմոբիլների համար»",
    "description": "5.3. «Ճանապարհ ավտոմոբիլների համար»",
    "imageUrl": "https://varord.am/images/sign/n5/5_3.png",
    "type": "5. ՀԱՏՈՒԿ ԹԵԼԱԴՐԱՆՔԻ ՆՇԱՆՆԵՐ"
  },
  {
    "title": "5.4. «Ավտոմոբիլների համար ճանապարհի վերջ»",
    "description": "5.4. «Ավտոմոբիլների համար ճանապարհի վերջ»",
    "imageUrl": "https://varord.am/images/sign/n5/5_4.png",
    "type": "5. ՀԱՏՈՒԿ ԹԵԼԱԴՐԱՆՔԻ ՆՇԱՆՆԵՐ"
  },
  {
    "title": "5.5. «Միակողմ երթևեկությամբ ճանապարհ»",
    "description": "5.5. «Միակողմ երթևեկությամբ ճանապարհ»",
    "imageUrl": "https://varord.am/images/sign/n5/5_5.png",
    "type": "5. ՀԱՏՈՒԿ ԹԵԼԱԴՐԱՆՔԻ ՆՇԱՆՆԵՐ"
  },
  {
    "title": "5.6. «Միակողմ երթևեկությամբ ճանապարհի վերջ»",
    "description": "5.6. «Միակողմ երթևեկությամբ ճանապարհի վերջ»",
    "imageUrl": "https://varord.am/images/sign/n5/5_6.png",
    "type": "5. ՀԱՏՈՒԿ ԹԵԼԱԴՐԱՆՔԻ ՆՇԱՆՆԵՐ"
  },
  {
    "title": "5.7.1. «Ելք դեպի միակողմ երթևեկությամբ ճանապարհ»",
    "description": "5.7.1. «Ելք դեպի միակողմ երթևեկությամբ ճանապարհ»",
    "imageUrl": "https://varord.am/images/sign/n5/5_7_1.png",
    "type": "5. ՀԱՏՈՒԿ ԹԵԼԱԴՐԱՆՔԻ ՆՇԱՆՆԵՐ"
  },
  {
    "title": "5.7.2. «Ելք դեպի միակողմ երթևեկությամբ ճանապարհ»",
    "description": "5.7.2. «Ելք դեպի միակողմ երթևեկությամբ ճանապարհ»",
    "imageUrl": "https://varord.am/images/sign/n5/5_7_2.png",
    "type": "5. ՀԱՏՈՒԿ ԹԵԼԱԴՐԱՆՔԻ ՆՇԱՆՆԵՐ"
  },
  {
    "title": "5.8. «Դարձափոխային երթևեկություն»",
    "description": "5.8. «Դարձափոխային երթևեկություն»",
    "imageUrl": "https://varord.am/images/sign/n5/5_8.png",
    "type": "5. ՀԱՏՈՒԿ ԹԵԼԱԴՐԱՆՔԻ ՆՇԱՆՆԵՐ"
  },
  {
    "title": "5.9. «Դարձափոխային երթևեկության վերջ»",
    "description": "5.9. «Դարձափոխային երթևեկության վերջ»",
    "imageUrl": "https://varord.am/images/sign/n5/5_9.png",
    "type": "5. ՀԱՏՈՒԿ ԹԵԼԱԴՐԱՆՔԻ ՆՇԱՆՆԵՐ"
  },
  {
    "title": "5.10. «Ելք դեպի դարձափոխային երթևեկությամբ ճանապարհ»",
    "description": "5.10. «Ելք դեպի դարձափոխային երթևեկությամբ ճանապարհ»",
    "imageUrl": "https://varord.am/images/sign/n5/5_10.png",
    "type": "5. ՀԱՏՈՒԿ ԹԵԼԱԴՐԱՆՔԻ ՆՇԱՆՆԵՐ"
  },
  {
    "title": "5.11. «Ընդհանուր օգտագործման տրանսպորտային միջոցների համար գոտիով ճանապարհ»",
    "description": "5.11. «Ընդհանուր օգտագործման տրանսպորտային միջոցների համար գոտիով ճանապարհ»",
    "imageUrl": "https://varord.am/images/sign/n5/5_11.png",
    "type": "5. ՀԱՏՈՒԿ ԹԵԼԱԴՐԱՆՔԻ ՆՇԱՆՆԵՐ"
  },
  {
    "title": "5.12. «Ընդհանուր օգտագործման տրանսպորտային միջոցների համար գոտիով ճանապարհի վերջ»",
    "description": "5.12. «Ընդհանուր օգտագործման տրանսպորտային միջոցների համար գոտիով ճանապարհի վերջ»",
    "imageUrl": "https://varord.am/images/sign/n5/5_12.png",
    "type": "5. ՀԱՏՈՒԿ ԹԵԼԱԴՐԱՆՔԻ ՆՇԱՆՆԵՐ"
  },
  {
    "title": "5.13.1. «Ելք դեպի ընդհանուր օգտագործման տրանսպորտային միջոցների համար գոտիով ճանապարհ»",
    "description": "5.13.1. «Ելք դեպի ընդհանուր օգտագործման տրանսպորտային միջոցների համար գոտիով ճանապարհ»",
    "imageUrl": "https://varord.am/images/sign/n5/5_13_1.png",
    "type": "5. ՀԱՏՈՒԿ ԹԵԼԱԴՐԱՆՔԻ ՆՇԱՆՆԵՐ"
  },
  {
    "title": "5.13.2. «Ելք դեպի ընդհանուր օգտագործման տրանսպորտային միջոցների համար գոտիով ճանապարհ»",
    "description": "5.13.2. «Ելք դեպի ընդհանուր օգտագործման տրանսպորտային միջոցների համար գոտիով ճանապարհ»",
    "imageUrl": "https://varord.am/images/sign/n5/5_13_2.png",
    "type": "5. ՀԱՏՈՒԿ ԹԵԼԱԴՐԱՆՔԻ ՆՇԱՆՆԵՐ"
  },
  {
    "title": "5.14. «Ընդհանուր օգտագործման տրանսպորտային միջոցների համար գոտի»",
    "description": "5.14. «Ընդհանուր օգտագործման տրանսպորտային միջոցների համար գոտի»",
    "imageUrl": "https://varord.am/images/sign/n5/5_14.png",
    "type": "5. ՀԱՏՈՒԿ ԹԵԼԱԴՐԱՆՔԻ ՆՇԱՆՆԵՐ"
  },
  {
    "title": "5.15.1. «Երթևեկության ուղղությունները գոտիներով»",
    "description": "5.15.1. «Երթևեկության ուղղությունները գոտիներով»",
    "imageUrl": "https://varord.am/images/sign/n5/5_15_1.png",
    "type": "5. ՀԱՏՈՒԿ ԹԵԼԱԴՐԱՆՔԻ ՆՇԱՆՆԵՐ"
  },
  {
    "title": "5.15.2. «Երթևեկության ուղղությունները գոտիով»",
    "description": "5.15.2. «Երթևեկության ուղղությունները գոտիով»",
    "imageUrl": "https://varord.am/images/sign/n5/5_15_2.png",
    "type": "5. ՀԱՏՈՒԿ ԹԵԼԱԴՐԱՆՔԻ ՆՇԱՆՆԵՐ"
  },
  {
    "title": "5.15.3. «Գոտու սկիզբ»",
    "description": "5.15.3. «Գոտու սկիզբ»",
    "imageUrl": "https://varord.am/images/sign/n5/5_15_3.png",
    "type": "5. ՀԱՏՈՒԿ ԹԵԼԱԴՐԱՆՔԻ ՆՇԱՆՆԵՐ"
  },
  {
    "title": "5.15.4. «Գոտու սկիզբ»",
    "description": "5.15.4. «Գոտու սկիզբ»",
    "imageUrl": "https://varord.am/images/sign/n5/5_15_4.png",
    "type": "5. ՀԱՏՈՒԿ ԹԵԼԱԴՐԱՆՔԻ ՆՇԱՆՆԵՐ"
  },
  {
    "title": "5.15.5. «Գոտու վերջ»",
    "description": "5.15.5. «Գոտու վերջ»",
    "imageUrl": "https://varord.am/images/sign/n5/5_15_5.png",
    "type": "5. ՀԱՏՈՒԿ ԹԵԼԱԴՐԱՆՔԻ ՆՇԱՆՆԵՐ"
  },
  {
    "title": "5.15.6. «Գոտու վերջ»",
    "description": "5.15.6. «Գոտու վերջ»",
    "imageUrl": "https://varord.am/images/sign/n5/5_15_6.png",
    "type": "5. ՀԱՏՈՒԿ ԹԵԼԱԴՐԱՆՔԻ ՆՇԱՆՆԵՐ"
  },
  {
    "title": "5.15.7. «Երթևեկության ուղղությունը գոտիներով»",
    "description": "5.15.7. «Երթևեկության ուղղությունը գոտիներով»",
    "imageUrl": "https://varord.am/images/sign/n5/5_15_7.png",
    "type": "5. ՀԱՏՈՒԿ ԹԵԼԱԴՐԱՆՔԻ ՆՇԱՆՆԵՐ"
  },
  {
    "title": "5.15.8. «Գոտիների քանակը»",
    "description": "5.15.8. «Գոտիների քանակը»",
    "imageUrl": "https://varord.am/images/sign/n5/5_15_8.png",
    "type": "5. ՀԱՏՈՒԿ ԹԵԼԱԴՐԱՆՔԻ ՆՇԱՆՆԵՐ"
  },
  {
    "title": "5.16. «Ավտոբուսի և (կամ) տրոլեյբուսի կանգառի տեղ»",
    "description": "5.16. «Ավտոբուսի և (կամ) տրոլեյբուսի կանգառի տեղ»",
    "imageUrl": "https://varord.am/images/sign/n5/5_16.png",
    "type": "5. ՀԱՏՈՒԿ ԹԵԼԱԴՐԱՆՔԻ ՆՇԱՆՆԵՐ"
  },
  {
    "title": "5.17. «Տրամվայի կանգառի տեղ»",
    "description": "5.17. «Տրամվայի կանգառի տեղ»",
    "imageUrl": "https://varord.am/images/sign/n5/5_17.png",
    "type": "5. ՀԱՏՈՒԿ ԹԵԼԱԴՐԱՆՔԻ ՆՇԱՆՆԵՐ"
  },
  {
    "title": "5.18. «Թեթև մարդատար տաքսիների կայանման տեղ»",
    "description": "5.18. «Թեթև մարդատար տաքսիների կայանման տեղ»",
    "imageUrl": "https://varord.am/images/sign/n5/5_18.png",
    "type": "5. ՀԱՏՈՒԿ ԹԵԼԱԴՐԱՆՔԻ ՆՇԱՆՆԵՐ"
  },
  {
    "title": "5.19.1. «Հետիոտնային անցում»",
    "description": "5.19.1. «Հետիոտնային անցում»",
    "imageUrl": "https://varord.am/images/sign/n5/5_19_1.png",
    "type": "5. ՀԱՏՈՒԿ ԹԵԼԱԴՐԱՆՔԻ ՆՇԱՆՆԵՐ"
  },
  {
    "title": "5.19.2. «Հետիոտնային անցում»",
    "description": "5.19.2. «Հետիոտնային անցում»",
    "imageUrl": "https://varord.am/images/sign/n5/5_19_2.png",
    "type": "5. ՀԱՏՈՒԿ ԹԵԼԱԴՐԱՆՔԻ ՆՇԱՆՆԵՐ"
  },
  {
    "title": "5.20. «Արհեստական անհարթություն»",
    "description": "5.20. «Արհեստական անհարթություն»",
    "imageUrl": "https://varord.am/images/sign/n5/5_20.png",
    "type": "5. ՀԱՏՈՒԿ ԹԵԼԱԴՐԱՆՔԻ ՆՇԱՆՆԵՐ"
  },
  {
    "title": "5.21. «Բնակելի գոտի»",
    "description": "5.21. «Բնակելի գոտի»",
    "imageUrl": "https://varord.am/images/sign/n5/5_21.png",
    "type": "5. ՀԱՏՈՒԿ ԹԵԼԱԴՐԱՆՔԻ ՆՇԱՆՆԵՐ"
  },
  {
    "title": "5.22. «Բնակելի գոտու վերջ»",
    "description": "5.22. «Բնակելի գոտու վերջ»",
    "imageUrl": "https://varord.am/images/sign/n5/5_22.png",
    "type": "5. ՀԱՏՈՒԿ ԹԵԼԱԴՐԱՆՔԻ ՆՇԱՆՆԵՐ"
  },
  {
    "title": "5.23.1. «Բնակավայրի սկիզբ»",
    "description": "5.23.1. «Բնակավայրի սկիզբ»",
    "imageUrl": "https://varord.am/images/sign/n5/5_23_1.png",
    "type": "5. ՀԱՏՈՒԿ ԹԵԼԱԴՐԱՆՔԻ ՆՇԱՆՆԵՐ"
  },
  {
    "title": "5.23.2. «Բնակավայրի սկիզբ»",
    "description": "5.23.2. «Բնակավայրի սկիզբ»",
    "imageUrl": "https://varord.am/images/sign/n5/5_23_2.png",
    "type": "5. ՀԱՏՈՒԿ ԹԵԼԱԴՐԱՆՔԻ ՆՇԱՆՆԵՐ"
  },
  {
    "title": "5.24.1. «Բնակավայրի վերջ»",
    "description": "5.24.1. «Բնակավայրի վերջ»",
    "imageUrl": "https://varord.am/images/sign/n5/5_24_1.png",
    "type": "5. ՀԱՏՈՒԿ ԹԵԼԱԴՐԱՆՔԻ ՆՇԱՆՆԵՐ"
  },
  {
    "title": "5.24.2. «Բնակավայրի վերջ»",
    "description": "5.24.2. «Բնակավայրի վերջ»",
    "imageUrl": "https://varord.am/images/sign/n5/5_24_2.png",
    "type": "5. ՀԱՏՈՒԿ ԹԵԼԱԴՐԱՆՔԻ ՆՇԱՆՆԵՐ"
  },
  {
    "title": "5.25. «Բնակավայրի սկիզբ»",
    "description": "5.25. «Բնակավայրի սկիզբ»",
    "imageUrl": "https://varord.am/images/sign/n5/5_25.png",
    "type": "5. ՀԱՏՈՒԿ ԹԵԼԱԴՐԱՆՔԻ ՆՇԱՆՆԵՐ"
  },
  {
    "title": "5.26. «Բնակավայրի վերջ»",
    "description": "5.26. «Բնակավայրի վերջ»",
    "imageUrl": "https://varord.am/images/sign/n5/5_26.png",
    "type": "5. ՀԱՏՈՒԿ ԹԵԼԱԴՐԱՆՔԻ ՆՇԱՆՆԵՐ"
  },
  {
    "title": "5.27. «Կայանման սահմանափակումով գոտի»",
    "description": "5.27. «Կայանման սահմանափակումով գոտի»",
    "imageUrl": "https://varord.am/images/sign/n5/5_27.png",
    "type": "5. ՀԱՏՈՒԿ ԹԵԼԱԴՐԱՆՔԻ ՆՇԱՆՆԵՐ"
  },
  {
    "title": "5.28. «Կայանման սահմանափակումով գոտու վերջ»",
    "description": "5.28. «Կայանման սահմանափակումով գոտու վերջ»",
    "imageUrl": "https://varord.am/images/sign/n5/5_28.png",
    "type": "5. ՀԱՏՈՒԿ ԹԵԼԱԴՐԱՆՔԻ ՆՇԱՆՆԵՐ"
  },
  {
    "title": "5.29. «Կարգավորվող կայանման գոտի»",
    "description": "5.29. «Կարգավորվող կայանման գոտի»",
    "imageUrl": "https://varord.am/images/sign/n5/5_29.png",
    "type": "5. ՀԱՏՈՒԿ ԹԵԼԱԴՐԱՆՔԻ ՆՇԱՆՆԵՐ"
  },
  {
    "title": "5.30. «Կարգավորվող կայանման գոտու վերջ»",
    "description": "5.30. «Կարգավորվող կայանման գոտու վերջ»",
    "imageUrl": "https://varord.am/images/sign/n5/5_30.png",
    "type": "5. ՀԱՏՈՒԿ ԹԵԼԱԴՐԱՆՔԻ ՆՇԱՆՆԵՐ"
  },
  {
    "title": "5.31. «Առավելագույն արագության սահմանափակումով գոտի»",
    "description": "5.31. «Առավելագույն արագության սահմանափակումով գոտի»",
    "imageUrl": "https://varord.am/images/sign/n5/5_31.png",
    "type": "5. ՀԱՏՈՒԿ ԹԵԼԱԴՐԱՆՔԻ ՆՇԱՆՆԵՐ"
  },
  {
    "title": "5.32. «Առավելագույն արագության սահմանափակումով գոտու վերջ»",
    "description": "5.32. «Առավելագույն արագության սահմանափակումով գոտու վերջ»",
    "imageUrl": "https://varord.am/images/sign/n5/5_32.png",
    "type": "5. ՀԱՏՈՒԿ ԹԵԼԱԴՐԱՆՔԻ ՆՇԱՆՆԵՐ"
  },
  {
    "title": "5.33. «Հետիոտնային գոտի»",
    "description": "5.33. «Հետիոտնային գոտի»",
    "imageUrl": "https://varord.am/images/sign/n5/5_33.png",
    "type": "5. ՀԱՏՈՒԿ ԹԵԼԱԴՐԱՆՔԻ ՆՇԱՆՆԵՐ"
  },
  {
    "title": "6.1. «Առավելագույն արագության ընդհանուր սահմանափակում»",
    "description": "6.1. «Առավելագույն արագության ընդհանուր սահմանափակում»",
    "imageUrl": "https://varord.am/images/sign/n6/6_1.png",
    "type": "6. ՏԵՂԵԿԱՏՎՈՒԹՅԱՆ ՆՇԱՆՆԵՐ"
  },
  {
    "title": "6.2. «Առաջարկվող արագություն»",
    "description": "6.2. «Առաջարկվող արագություն»",
    "imageUrl": "https://varord.am/images/sign/n6/6_2.png",
    "type": "6. ՏԵՂԵԿԱՏՎՈՒԹՅԱՆ ՆՇԱՆՆԵՐ"
  },
  {
    "title": "6.3.1. «Հետադարձի տեղ»",
    "description": "6.3.1. «Հետադարձի տեղ»",
    "imageUrl": "https://varord.am/images/sign/n6/6_3_1.png",
    "type": "6. ՏԵՂԵԿԱՏՎՈՒԹՅԱՆ ՆՇԱՆՆԵՐ"
  },
  {
    "title": "6.3.2. «Հետադարձի գոտի»",
    "description": "6.3.2. «Հետադարձի գոտի»",
    "imageUrl": "https://varord.am/images/sign/n6/6_3_2.png",
    "type": "6. ՏԵՂԵԿԱՏՎՈՒԹՅԱՆ ՆՇԱՆՆԵՐ"
  },
  {
    "title": "6.4. «Կայանման տեղ»",
    "description": "6.4. «Կայանման տեղ»",
    "imageUrl": "https://varord.am/images/sign/n6/6_4.png",
    "type": "6. ՏԵՂԵԿԱՏՎՈՒԹՅԱՆ ՆՇԱՆՆԵՐ"
  },
  {
    "title": "6.5. «Վթարային կանգառի գոտի»",
    "description": "6.5. «Վթարային կանգառի գոտի»",
    "imageUrl": "https://varord.am/images/sign/n6/6_5.png",
    "type": "6. ՏԵՂԵԿԱՏՎՈՒԹՅԱՆ ՆՇԱՆՆԵՐ"
  },
  {
    "title": "6.6. «Ստորգետնյա հետիոտնային անցում»",
    "description": "6.6. «Ստորգետնյա հետիոտնային անցում»",
    "imageUrl": "https://varord.am/images/sign/n6/6_6.png",
    "type": "6. ՏԵՂԵԿԱՏՎՈՒԹՅԱՆ ՆՇԱՆՆԵՐ"
  },
  {
    "title": "6.7. «Վերգետնյա հետիոտնային անցում»",
    "description": "6.7. «Վերգետնյա հետիոտնային անցում»",
    "imageUrl": "https://varord.am/images/sign/n6/6_7.png",
    "type": "6. ՏԵՂԵԿԱՏՎՈՒԹՅԱՆ ՆՇԱՆՆԵՐ"
  },
  {
    "title": "6.8.1. «Փակուղի»",
    "description": "6.8.1. «Փակուղի»",
    "imageUrl": "https://varord.am/images/sign/n6/6_8_1.png",
    "type": "6. ՏԵՂԵԿԱՏՎՈՒԹՅԱՆ ՆՇԱՆՆԵՐ"
  },
  {
    "title": "6.8.2. «Փակուղի»",
    "description": "6.8.2. «Փակուղի»",
    "imageUrl": "https://varord.am/images/sign/n6/6_8_2.png",
    "type": "6. ՏԵՂԵԿԱՏՎՈՒԹՅԱՆ ՆՇԱՆՆԵՐ"
  },
  {
    "title": "6.8.3. «Փակուղի»",
    "description": "6.8.3. «Փակուղի»",
    "imageUrl": "https://varord.am/images/sign/n6/6_8_3.png",
    "type": "6. ՏԵՂԵԿԱՏՎՈՒԹՅԱՆ ՆՇԱՆՆԵՐ"
  },
  {
    "title": "6.9.1. «Ուղղությունների նախնական ցուցիչ»",
    "description": "6.9.1. «Ուղղությունների նախնական ցուցիչ»",
    "imageUrl": "https://varord.am/images/sign/n6/6_9_1_1.png",
    "type": "6. ՏԵՂԵԿԱՏՎՈՒԹՅԱՆ ՆՇԱՆՆԵՐ"
  },
  {
    "title": "6.9.1. «Ուղղությունների նախնական ցուցիչ»",
    "description": "6.9.1. «Ուղղությունների նախնական ցուցիչ»",
    "imageUrl": "https://varord.am/images/sign/n6/6_9_1_2.png",
    "type": "6. ՏԵՂԵԿԱՏՎՈՒԹՅԱՆ ՆՇԱՆՆԵՐ"
  },
  {
    "title": "6.9.1. «Ուղղությունների նախնական ցուցիչ»",
    "description": "6.9.1. «Ուղղությունների նախնական ցուցիչ»",
    "imageUrl": "https://varord.am/images/sign/n6/6_9_1_3.png",
    "type": "6. ՏԵՂԵԿԱՏՎՈՒԹՅԱՆ ՆՇԱՆՆԵՐ"
  },
  {
    "title": "6.9.1. «Ուղղությունների նախնական ցուցիչ»",
    "description": "6.9.1. «Ուղղությունների նախնական ցուցիչ»",
    "imageUrl": "https://varord.am/images/sign/n6/6_9_1_4.png",
    "type": "6. ՏԵՂԵԿԱՏՎՈՒԹՅԱՆ ՆՇԱՆՆԵՐ"
  },
  {
    "title": "6.9.2. «Ուղղությունների նախնական ցուցիչ»",
    "description": "6.9.2. «Ուղղությունների նախնական ցուցիչ»",
    "imageUrl": "https://varord.am/images/sign/n6/6_9_2_1.png",
    "type": "6. ՏԵՂԵԿԱՏՎՈՒԹՅԱՆ ՆՇԱՆՆԵՐ"
  },
  {
    "title": "6.9.2. «Ուղղությունների նախնական ցուցիչ»",
    "description": "6.9.2. «Ուղղությունների նախնական ցուցիչ»",
    "imageUrl": "https://varord.am/images/sign/n6/6_9_2_2.png",
    "type": "6. ՏԵՂԵԿԱՏՎՈՒԹՅԱՆ ՆՇԱՆՆԵՐ"
  },
  {
    "title": "6.9.2. «Ուղղությունների նախնական ցուցիչ»",
    "description": "6.9.2. «Ուղղությունների նախնական ցուցիչ»",
    "imageUrl": "https://varord.am/images/sign/n6/6_9_2_3.png",
    "type": "6. ՏԵՂԵԿԱՏՎՈՒԹՅԱՆ ՆՇԱՆՆԵՐ"
  },
  {
    "title": "6.9.3. «Երթևեկության սխեմա»",
    "description": "6.9.3. «Երթևեկության սխեմա»",
    "imageUrl": "https://varord.am/images/sign/n6/6_9_3.png",
    "type": "6. ՏԵՂԵԿԱՏՎՈՒԹՅԱՆ ՆՇԱՆՆԵՐ"
  },
  {
    "title": "6.10.1. «Ուղղությունների ցուցիչ»",
    "description": "6.10.1. «Ուղղությունների ցուցիչ»",
    "imageUrl": "https://varord.am/images/sign/n6/6_10_1_1.png",
    "type": "6. ՏԵՂԵԿԱՏՎՈՒԹՅԱՆ ՆՇԱՆՆԵՐ"
  },
  {
    "title": "6.10.1. «Ուղղությունների ցուցիչ»",
    "description": "6.10.1. «Ուղղությունների ցուցիչ»",
    "imageUrl": "https://varord.am/images/sign/n6/6_10_1_2.png",
    "type": "6. ՏԵՂԵԿԱՏՎՈՒԹՅԱՆ ՆՇԱՆՆԵՐ"
  },
  {
    "title": "6.10.2. «Ուղղության ցուցիչ»",
    "description": "6.10.2. «Ուղղության ցուցիչ»",
    "imageUrl": "https://varord.am/images/sign/n6/6_10_2_1.png",
    "type": "6. ՏԵՂԵԿԱՏՎՈՒԹՅԱՆ ՆՇԱՆՆԵՐ"
  },
  {
    "title": "6.10.2. «Ուղղության ցուցիչ»",
    "description": "6.10.2. «Ուղղության ցուցիչ»",
    "imageUrl": "https://varord.am/images/sign/n6/6_10_2_2.png",
    "type": "6. ՏԵՂԵԿԱՏՎՈՒԹՅԱՆ ՆՇԱՆՆԵՐ"
  },
  {
    "title": "6.11. «Օբյեկտի անվանում»",
    "description": "6.11. «Օբյեկտի անվանում»",
    "imageUrl": "https://varord.am/images/sign/n6/6_11.png",
    "type": "6. ՏԵՂԵԿԱՏՎՈՒԹՅԱՆ ՆՇԱՆՆԵՐ"
  },
  {
    "title": "6.12. «Հեռավորությունների ցուցիչ»",
    "description": "6.12. «Հեռավորությունների ցուցիչ»",
    "imageUrl": "https://varord.am/images/sign/n6/6_12.png",
    "type": "6. ՏԵՂԵԿԱՏՎՈՒԹՅԱՆ ՆՇԱՆՆԵՐ"
  },
  {
    "title": "6.13. «Կիլոմետրային նշան»",
    "description": "6.13. «Կիլոմետրային նշան»",
    "imageUrl": "https://varord.am/images/sign/n6/6_13.png",
    "type": "6. ՏԵՂԵԿԱՏՎՈՒԹՅԱՆ ՆՇԱՆՆԵՐ"
  },
  {
    "title": "6.14.2. «Երթուղու համարը»",
    "description": "6.14.2. «Երթուղու համարը»",
    "imageUrl": "https://varord.am/images/sign/n6/6_14_2.png",
    "type": "6. ՏԵՂԵԿԱՏՎՈՒԹՅԱՆ ՆՇԱՆՆԵՐ"
  },
  {
    "title": "6.15. «Երթևեկության ուղղություն բեռնատար ավտոմոբիլների համար»",
    "description": "6.15. «Երթևեկության ուղղություն բեռնատար ավտոմոբիլների համար»",
    "imageUrl": "https://varord.am/images/sign/n6/6_15_1.png",
    "type": "6. ՏԵՂԵԿԱՏՎՈՒԹՅԱՆ ՆՇԱՆՆԵՐ"
  },
  {
    "title": "6.15. «Երթևեկության ուղղություն բեռնատար ավտոմոբիլների համար»",
    "description": "6.15. «Երթևեկության ուղղություն բեռնատար ավտոմոբիլների համար»",
    "imageUrl": "https://varord.am/images/sign/n6/6_15_2.png",
    "type": "6. ՏԵՂԵԿԱՏՎՈՒԹՅԱՆ ՆՇԱՆՆԵՐ"
  },
  {
    "title": "6.15. «Երթևեկության ուղղություն բեռնատար ավտոմոբիլների համար»",
    "description": "6.15. «Երթևեկության ուղղություն բեռնատար ավտոմոբիլների համար»",
    "imageUrl": "https://varord.am/images/sign/n6/6_15_3.png",
    "type": "6. ՏԵՂԵԿԱՏՎՈՒԹՅԱՆ ՆՇԱՆՆԵՐ"
  },
  {
    "title": "6.16. «Կանգ-գիծ»",
    "description": "6.16. «Կանգ-գիծ»",
    "imageUrl": "https://varord.am/images/sign/n6/6_16.png",
    "type": "6. ՏԵՂԵԿԱՏՎՈՒԹՅԱՆ ՆՇԱՆՆԵՐ"
  },
  {
    "title": "6.17. «Շրջանցման սխեմա»",
    "description": "6.17. «Շրջանցման սխեմա»",
    "imageUrl": "https://varord.am/images/sign/n6/6_17.png",
    "type": "6. ՏԵՂԵԿԱՏՎՈՒԹՅԱՆ ՆՇԱՆՆԵՐ"
  },
  {
    "title": "6.18. «Շրջանցման ուղղություն»",
    "description": "6.18. «Շրջանցման ուղղություն»",
    "imageUrl": "https://varord.am/images/sign/n6/6_18_1.png",
    "type": "6. ՏԵՂԵԿԱՏՎՈՒԹՅԱՆ ՆՇԱՆՆԵՐ"
  },
  {
    "title": "6.18. «Շրջանցման ուղղություն»",
    "description": "6.18. «Շրջանցման ուղղություն»",
    "imageUrl": "https://varord.am/images/sign/n6/6_18_2.png",
    "type": "6. ՏԵՂԵԿԱՏՎՈՒԹՅԱՆ ՆՇԱՆՆԵՐ"
  },
  {
    "title": "6.18. «Շրջանցման ուղղություն»",
    "description": "6.18. «Շրջանցման ուղղություն»",
    "imageUrl": "https://varord.am/images/sign/n6/6_18_3.png",
    "type": "6. ՏԵՂԵԿԱՏՎՈՒԹՅԱՆ ՆՇԱՆՆԵՐ"
  },
  {
    "title": "6.19. «Այլ երթևեկելի մաս վերադասավորվելու նախնական ցուցիչ»",
    "description": "6.19. «Այլ երթևեկելի մաս վերադասավորվելու նախնական ցուցիչ»",
    "imageUrl": "https://varord.am/images/sign/n6/6_19_1.png",
    "type": "6. ՏԵՂԵԿԱՏՎՈՒԹՅԱՆ ՆՇԱՆՆԵՐ"
  },
  {
    "title": "6.19. «Այլ երթևեկելի մաս վերադասավորվելու նախնական ցուցիչ»",
    "description": "6.19. «Այլ երթևեկելի մաս վերադասավորվելու նախնական ցուցիչ»",
    "imageUrl": "https://varord.am/images/sign/n6/6_19_2.png",
    "type": "6. ՏԵՂԵԿԱՏՎՈՒԹՅԱՆ ՆՇԱՆՆԵՐ"
  },
  {
    "title": "7.1. «Առաջին բժշկական օգնության կետ»",
    "description": "7.1. «Առաջին բժշկական օգնության կետ»",
    "imageUrl": "https://varord.am/images/sign/n7/7_1.png",
    "type": "7. ՍՊԱՍԱՐԿՄԱՆ ՆՇԱՆՆԵՐ"
  },
  {
    "title": "7.2. «Հիվանդանոց»",
    "description": "7.2. «Հիվանդանոց»",
    "imageUrl": "https://varord.am/images/sign/n7/7_2.png",
    "type": "7. ՍՊԱՍԱՐԿՄԱՆ ՆՇԱՆՆԵՐ"
  },
  {
    "title": "7.3. «Ավտոլցավորման կայան»",
    "description": "7.3. «Ավտոլցավորման կայան»",
    "imageUrl": "https://varord.am/images/sign/n7/7_3.png",
    "type": "7. ՍՊԱՍԱՐԿՄԱՆ ՆՇԱՆՆԵՐ"
  },
  {
    "title": "7.4. «Ավտոմոբիլների տեխնիկական սպասարկում»",
    "description": "7.4. «Ավտոմոբիլների տեխնիկական սպասարկում»",
    "imageUrl": "https://varord.am/images/sign/n7/7_4.png",
    "type": "7. ՍՊԱՍԱՐԿՄԱՆ ՆՇԱՆՆԵՐ"
  },
  {
    "title": "7.5. «Ավտոմոբիլների լվացում»",
    "description": "7.5. «Ավտոմոբիլների լվացում»",
    "imageUrl": "https://varord.am/images/sign/n7/7_5.png",
    "type": "7. ՍՊԱՍԱՐԿՄԱՆ ՆՇԱՆՆԵՐ"
  },
  {
    "title": "7.6. «Հեռախոս»",
    "description": "7.6. «Հեռախոս»",
    "imageUrl": "https://varord.am/images/sign/n7/7_6.png",
    "type": "7. ՍՊԱՍԱՐԿՄԱՆ ՆՇԱՆՆԵՐ"
  },
  {
    "title": "7.7. «Սննդի կետ»",
    "description": "7.7. «Սննդի կետ»",
    "imageUrl": "https://varord.am/images/sign/n7/7_7.png",
    "type": "7. ՍՊԱՍԱՐԿՄԱՆ ՆՇԱՆՆԵՐ"
  },
  {
    "title": "7.8. «Խմելու ջուր»",
    "description": "7.8. «Խմելու ջուր»",
    "imageUrl": "https://varord.am/images/sign/n7/7_8.png",
    "type": "7. ՍՊԱՍԱՐԿՄԱՆ ՆՇԱՆՆԵՐ"
  },
  {
    "title": "7.9. «Հյուրանոց կամ մոթել»",
    "description": "7.9. «Հյուրանոց կամ մոթել»",
    "imageUrl": "https://varord.am/images/sign/n7/7_9.png",
    "type": "7. ՍՊԱՍԱՐԿՄԱՆ ՆՇԱՆՆԵՐ"
  },
  {
    "title": "7.10. «Հանգրվան»",
    "description": "7.10. «Հանգրվան»",
    "imageUrl": "https://varord.am/images/sign/n7/7_10.png",
    "type": "7. ՍՊԱՍԱՐԿՄԱՆ ՆՇԱՆՆԵՐ"
  },
  {
    "title": "7.11. «Հանգստի վայր»",
    "description": "7.11. «Հանգստի վայր»",
    "imageUrl": "https://varord.am/images/sign/n7/7_11.png",
    "type": "7. ՍՊԱՍԱՐԿՄԱՆ ՆՇԱՆՆԵՐ"
  },
  {
    "title": "7.12. «Ճանապարհային ոստիկանության ճանապարհապարեկային ծառայության պահակետ»",
    "description": "7.12. «Ճանապարհային ոստիկանության ճանապարհապարեկային ծառայության պահակետ»",
    "imageUrl": "https://varord.am/images/sign/n7/7_12.png",
    "type": "7. ՍՊԱՍԱՐԿՄԱՆ ՆՇԱՆՆԵՐ"
  },
  {
    "title": "7.13. «Ոստիկանություն»",
    "description": "7.13. «Ոստիկանություն»",
    "imageUrl": "https://varord.am/images/sign/n7/7_13.png",
    "type": "7. ՍՊԱՍԱՐԿՄԱՆ ՆՇԱՆՆԵՐ"
  },
  {
    "title": "7.14. «Միջազգային ավտոմոբիլային փոխադրումների հսկման կետ»",
    "description": "7.14. «Միջազգային ավտոմոբիլային փոխադրումների հսկման կետ»",
    "imageUrl": "https://varord.am/images/sign/n7/7_14.png",
    "type": "7. ՍՊԱՍԱՐԿՄԱՆ ՆՇԱՆՆԵՐ"
  },
  {
    "title": "7.15. «Ճանապարհային երթևեկության մասին տեղեկություն հաղորդող ռադիոկայանի գործողության գոտի»",
    "description": "7.15. «Ճանապարհային երթևեկության մասին տեղեկություն հաղորդող ռադիոկայանի գործողության գոտի»",
    "imageUrl": "https://varord.am/images/sign/n7/7_15.png",
    "type": "7. ՍՊԱՍԱՐԿՄԱՆ ՆՇԱՆՆԵՐ"
  },
  {
    "title": "7.16. «Վթարային ծառայությունների հետ ռադիոկապի գոտի»",
    "description": "7.16. «Վթարային ծառայությունների հետ ռադիոկապի գոտի»",
    "imageUrl": "https://varord.am/images/sign/n7/7_16.png",
    "type": "7. ՍՊԱՍԱՐԿՄԱՆ ՆՇԱՆՆԵՐ"
  },
  {
    "title": "7.17. «Լողավազան կամ լողափ»",
    "description": "7.17. «Լողավազան կամ լողափ»",
    "imageUrl": "https://varord.am/images/sign/n7/7_17.png",
    "type": "7. ՍՊԱՍԱՐԿՄԱՆ ՆՇԱՆՆԵՐ"
  },
  {
    "title": "8.1.1. «Հեռավորություն մինչև օբյեկտ»",
    "description": "8.1.1. «Հեռավորություն մինչև օբյեկտ»",
    "imageUrl": "https://varord.am/images/sign/n8/8_1_1.png",
    "type": "8. ԼՐԱՑՈՒՑԻՉ ՏԵՂԵԿԱՏՎՈՒԹՅԱՆ ՆՇԱՆՆԵՐ (ՑՈՒՑԱՆԱԿՆԵՐ)"
  },
  {
    "title": "8.1.2. «Հեռավորություն մինչև օբյեկտ».",
    "description": "8.1.2. «Հեռավորություն մինչև օբյեկտ».",
    "imageUrl": "https://varord.am/images/sign/n8/8_1_2.png",
    "type": "8. ԼՐԱՑՈՒՑԻՉ ՏԵՂԵԿԱՏՎՈՒԹՅԱՆ ՆՇԱՆՆԵՐ (ՑՈՒՑԱՆԱԿՆԵՐ)"
  },
  {
    "title": "8.1.3. «Հեռավորություն մինչև օբյեկտ»",
    "description": "8.1.3. «Հեռավորություն մինչև օբյեկտ»",
    "imageUrl": "https://varord.am/images/sign/n8/8_1_3.png",
    "type": "8. ԼՐԱՑՈՒՑԻՉ ՏԵՂԵԿԱՏՎՈՒԹՅԱՆ ՆՇԱՆՆԵՐ (ՑՈՒՑԱՆԱԿՆԵՐ)"
  },
  {
    "title": "8.1.4. «Հեռավորություն մինչև օբյեկտ»",
    "description": "8.1.4. «Հեռավորություն մինչև օբյեկտ»",
    "imageUrl": "https://varord.am/images/sign/n8/8_1_4.png",
    "type": "8. ԼՐԱՑՈՒՑԻՉ ՏԵՂԵԿԱՏՎՈՒԹՅԱՆ ՆՇԱՆՆԵՐ (ՑՈՒՑԱՆԱԿՆԵՐ)"
  },
  {
    "title": "8.2.1. «Ազդման գոտի»",
    "description": "8.2.1. «Ազդման գոտի»",
    "imageUrl": "https://varord.am/images/sign/n8/8_2_1.png",
    "type": "8. ԼՐԱՑՈՒՑԻՉ ՏԵՂԵԿԱՏՎՈՒԹՅԱՆ ՆՇԱՆՆԵՐ (ՑՈՒՑԱՆԱԿՆԵՐ)"
  },
  {
    "title": "8.2.2. «Ազդման գոտի». ",
    "description": "8.2.2. «Ազդման գոտի». ",
    "imageUrl": "https://varord.am/images/sign/n8/8_2_2.png",
    "type": "8. ԼՐԱՑՈՒՑԻՉ ՏԵՂԵԿԱՏՎՈՒԹՅԱՆ ՆՇԱՆՆԵՐ (ՑՈՒՑԱՆԱԿՆԵՐ)"
  },
  {
    "title": "8.2.3. «Ազդման գոտի»",
    "description": "8.2.3. «Ազդման գոտի»",
    "imageUrl": "https://varord.am/images/sign/n8/8_2_3.png",
    "type": "8. ԼՐԱՑՈՒՑԻՉ ՏԵՂԵԿԱՏՎՈՒԹՅԱՆ ՆՇԱՆՆԵՐ (ՑՈՒՑԱՆԱԿՆԵՐ)"
  },
  {
    "title": "8.2.4. «Ազդման գոտի»",
    "description": "8.2.4. «Ազդման գոտի»",
    "imageUrl": "https://varord.am/images/sign/n8/8_2_4.png",
    "type": "8. ԼՐԱՑՈՒՑԻՉ ՏԵՂԵԿԱՏՎՈՒԹՅԱՆ ՆՇԱՆՆԵՐ (ՑՈՒՑԱՆԱԿՆԵՐ)"
  },
  {
    "title": "8.2.5. «Ազդման գոտի»",
    "description": "8.2.5. «Ազդման գոտի»",
    "imageUrl": "https://varord.am/images/sign/n8/8_2_5.png",
    "type": "8. ԼՐԱՑՈՒՑԻՉ ՏԵՂԵԿԱՏՎՈՒԹՅԱՆ ՆՇԱՆՆԵՐ (ՑՈՒՑԱՆԱԿՆԵՐ)"
  },
  {
    "title": "8.2.6. «Ազդման գոտի»",
    "description": "8.2.6. «Ազդման գոտի»",
    "imageUrl": "https://varord.am/images/sign/n8/8_2_6.png",
    "type": "8. ԼՐԱՑՈՒՑԻՉ ՏԵՂԵԿԱՏՎՈՒԹՅԱՆ ՆՇԱՆՆԵՐ (ՑՈՒՑԱՆԱԿՆԵՐ)"
  },
  {
    "title": "8.3.1. «Ազդման ուղղություն»",
    "description": "8.3.1. «Ազդման ուղղություն»",
    "imageUrl": "https://varord.am/images/sign/n8/8_3_1.png",
    "type": "8. ԼՐԱՑՈՒՑԻՉ ՏԵՂԵԿԱՏՎՈՒԹՅԱՆ ՆՇԱՆՆԵՐ (ՑՈՒՑԱՆԱԿՆԵՐ)"
  },
  {
    "title": "8.3.2. «Ազդման ուղղություն»",
    "description": "8.3.2. «Ազդման ուղղություն»",
    "imageUrl": "https://varord.am/images/sign/n8/8_3_2.png",
    "type": "8. ԼՐԱՑՈՒՑԻՉ ՏԵՂԵԿԱՏՎՈՒԹՅԱՆ ՆՇԱՆՆԵՐ (ՑՈՒՑԱՆԱԿՆԵՐ)"
  },
  {
    "title": "8.3.3. «Ազդման ուղղություն»",
    "description": "8.3.3. «Ազդման ուղղություն»",
    "imageUrl": "https://varord.am/images/sign/n8/8_3_3.png",
    "type": "8. ԼՐԱՑՈՒՑԻՉ ՏԵՂԵԿԱՏՎՈՒԹՅԱՆ ՆՇԱՆՆԵՐ (ՑՈՒՑԱՆԱԿՆԵՐ)"
  },
  {
    "title": "8.4.1. «Տրանսպորտային միջոցի տեսակը»",
    "description": "8.4.1. «Տրանսպորտային միջոցի տեսակը»",
    "imageUrl": "https://varord.am/images/sign/n8/8_4_1.png",
    "type": "8. ԼՐԱՑՈՒՑԻՉ ՏԵՂԵԿԱՏՎՈՒԹՅԱՆ ՆՇԱՆՆԵՐ (ՑՈՒՑԱՆԱԿՆԵՐ)"
  },
  {
    "title": "8.4.2. «Տրանսպորտային միջոցի տեսակը»",
    "description": "8.4.2. «Տրանսպորտային միջոցի տեսակը»",
    "imageUrl": "https://varord.am/images/sign/n8/8_4_2.png",
    "type": "8. ԼՐԱՑՈՒՑԻՉ ՏԵՂԵԿԱՏՎՈՒԹՅԱՆ ՆՇԱՆՆԵՐ (ՑՈՒՑԱՆԱԿՆԵՐ)"
  },
  {
    "title": "8.4.3. «Տրանսպորտային միջոցի տեսակը»",
    "description": "8.4.3. «Տրանսպորտային միջոցի տեսակը»",
    "imageUrl": "https://varord.am/images/sign/n8/8_4_3.png",
    "type": "8. ԼՐԱՑՈՒՑԻՉ ՏԵՂԵԿԱՏՎՈՒԹՅԱՆ ՆՇԱՆՆԵՐ (ՑՈՒՑԱՆԱԿՆԵՐ)"
  },
  {
    "title": "8.4.3.1 «Տրանսպորտային միջոցի տեսակը»",
    "description": "8.4.3.1 «Տրանսպորտային միջոցի տեսակը»",
    "imageUrl": "https://varord.am/images/sign/n8/8_4_3_1.png",
    "type": "8. ԼՐԱՑՈՒՑԻՉ ՏԵՂԵԿԱՏՎՈՒԹՅԱՆ ՆՇԱՆՆԵՐ (ՑՈՒՑԱՆԱԿՆԵՐ)"
  },
  {
    "title": "8.4.4. «Տրանսպորտային միջոցի տեսակը»",
    "description": "8.4.4. «Տրանսպորտային միջոցի տեսակը»",
    "imageUrl": "https://varord.am/images/sign/n8/8_4_4.png",
    "type": "8. ԼՐԱՑՈՒՑԻՉ ՏԵՂԵԿԱՏՎՈՒԹՅԱՆ ՆՇԱՆՆԵՐ (ՑՈՒՑԱՆԱԿՆԵՐ)"
  },
  {
    "title": "8.4.5. «Տրանսպորտային միջոցի տեսակը»",
    "description": "8.4.5. «Տրանսպորտային միջոցի տեսակը»",
    "imageUrl": "https://varord.am/images/sign/n8/8_4_5.png",
    "type": "8. ԼՐԱՑՈՒՑԻՉ ՏԵՂԵԿԱՏՎՈՒԹՅԱՆ ՆՇԱՆՆԵՐ (ՑՈՒՑԱՆԱԿՆԵՐ)"
  },
  {
    "title": "8.4.6. «Տրանսպորտային միջոցի տեսակը»",
    "description": "8.4.6. «Տրանսպորտային միջոցի տեսակը»",
    "imageUrl": "https://varord.am/images/sign/n8/8_4_6.png",
    "type": "8. ԼՐԱՑՈՒՑԻՉ ՏԵՂԵԿԱՏՎՈՒԹՅԱՆ ՆՇԱՆՆԵՐ (ՑՈՒՑԱՆԱԿՆԵՐ)"
  },
  {
    "title": "8.4.7. «Տրանսպորտային միջոցի տեսակը»",
    "description": "8.4.7. «Տրանսպորտային միջոցի տեսակը»",
    "imageUrl": "https://varord.am/images/sign/n8/8_4_7.png",
    "type": "8. ԼՐԱՑՈՒՑԻՉ ՏԵՂԵԿԱՏՎՈՒԹՅԱՆ ՆՇԱՆՆԵՐ (ՑՈՒՑԱՆԱԿՆԵՐ)"
  },
  {
    "title": "8.4.8. «Տրանսպորտային միջոցի տեսակը». ",
    "description": "8.4.8. «Տրանսպորտային միջոցի տեսակը». ",
    "imageUrl": "https://varord.am/images/sign/n8/8_4_8.png",
    "type": "8. ԼՐԱՑՈՒՑԻՉ ՏԵՂԵԿԱՏՎՈՒԹՅԱՆ ՆՇԱՆՆԵՐ (ՑՈՒՑԱՆԱԿՆԵՐ)"
  },
  {
    "title": "8.5.1. «Շաբաթ, կիրակի և տոն օրեր»",
    "description": "8.5.1. «Շաբաթ, կիրակի և տոն օրեր»",
    "imageUrl": "https://varord.am/images/sign/n8/8_5_1.png",
    "type": "8. ԼՐԱՑՈՒՑԻՉ ՏԵՂԵԿԱՏՎՈՒԹՅԱՆ ՆՇԱՆՆԵՐ (ՑՈՒՑԱՆԱԿՆԵՐ)"
  },
  {
    "title": "8.5.2. «Աշխատանքային օրեր»",
    "description": "8.5.2. «Աշխատանքային օրեր»",
    "imageUrl": "https://varord.am/images/sign/n8/8_5_2.png",
    "type": "8. ԼՐԱՑՈՒՑԻՉ ՏԵՂԵԿԱՏՎՈՒԹՅԱՆ ՆՇԱՆՆԵՐ (ՑՈՒՑԱՆԱԿՆԵՐ)"
  },
  {
    "title": "8.5.3. «Շաբաթվա օրեր»",
    "description": "8.5.3. «Շաբաթվա օրեր»",
    "imageUrl": "https://varord.am/images/sign/n8/8_5_3.png",
    "type": "8. ԼՐԱՑՈՒՑԻՉ ՏԵՂԵԿԱՏՎՈՒԹՅԱՆ ՆՇԱՆՆԵՐ (ՑՈՒՑԱՆԱԿՆԵՐ)"
  },
  {
    "title": "8.5.4. «Գործողության ժամանակ»",
    "description": "8.5.4. «Գործողության ժամանակ»",
    "imageUrl": "https://varord.am/images/sign/n8/8_5_4.png",
    "type": "8. ԼՐԱՑՈՒՑԻՉ ՏԵՂԵԿԱՏՎՈՒԹՅԱՆ ՆՇԱՆՆԵՐ (ՑՈՒՑԱՆԱԿՆԵՐ)"
  },
  {
    "title": "8.5.5. «Գործողության ժամանակ»",
    "description": "8.5.5. «Գործողության ժամանակ»",
    "imageUrl": "https://varord.am/images/sign/n8/8_5_5.png",
    "type": "8. ԼՐԱՑՈՒՑԻՉ ՏԵՂԵԿԱՏՎՈՒԹՅԱՆ ՆՇԱՆՆԵՐ (ՑՈՒՑԱՆԱԿՆԵՐ)"
  },
  {
    "title": "8.5.6. «Գործողության ժամանակ»",
    "description": "8.5.6. «Գործողության ժամանակ»",
    "imageUrl": "https://varord.am/images/sign/n8/8_5_6.png",
    "type": "8. ԼՐԱՑՈՒՑԻՉ ՏԵՂԵԿԱՏՎՈՒԹՅԱՆ ՆՇԱՆՆԵՐ (ՑՈՒՑԱՆԱԿՆԵՐ)"
  },
  {
    "title": "8.5.7. «Գործողության ժամանակ»",
    "description": "8.5.7. «Գործողության ժամանակ»",
    "imageUrl": "https://varord.am/images/sign/n8/8_5_7.png",
    "type": "8. ԼՐԱՑՈՒՑԻՉ ՏԵՂԵԿԱՏՎՈՒԹՅԱՆ ՆՇԱՆՆԵՐ (ՑՈՒՑԱՆԱԿՆԵՐ)"
  },
  {
    "title": "8.6.2. «Տրանսպորտային միջոցի կանգնեցման ձևը կայանման տեղերում»",
    "description": "8.6.2. «Տրանսպորտային միջոցի կանգնեցման ձևը կայանման տեղերում»",
    "imageUrl": "https://varord.am/images/sign/n8/8_6_2.png",
    "type": "8. ԼՐԱՑՈՒՑԻՉ ՏԵՂԵԿԱՏՎՈՒԹՅԱՆ ՆՇԱՆՆԵՐ (ՑՈՒՑԱՆԱԿՆԵՐ)"
  },
  {
    "title": "8.6.3. «Տրանսպորտային միջոցի կանգնեցման ձևը կայանման տեղերում»",
    "description": "8.6.3. «Տրանսպորտային միջոցի կանգնեցման ձևը կայանման տեղերում»",
    "imageUrl": "https://varord.am/images/sign/n8/8_6_3.png",
    "type": "8. ԼՐԱՑՈՒՑԻՉ ՏԵՂԵԿԱՏՎՈՒԹՅԱՆ ՆՇԱՆՆԵՐ (ՑՈՒՑԱՆԱԿՆԵՐ)"
  },
  {
    "title": "8.6.4. «Տրանսպորտային միջոցի կանգնեցման ձևը կայանման տեղերում»",
    "description": "8.6.4. «Տրանսպորտային միջոցի կանգնեցման ձևը կայանման տեղերում»",
    "imageUrl": "https://varord.am/images/sign/n8/8_6_4.png",
    "type": "8. ԼՐԱՑՈՒՑԻՉ ՏԵՂԵԿԱՏՎՈՒԹՅԱՆ ՆՇԱՆՆԵՐ (ՑՈՒՑԱՆԱԿՆԵՐ)"
  },
  {
    "title": "8.6.5. «Տրանսպորտային միջոցի կանգնեցման ձևը կայանման տեղերում»",
    "description": "8.6.5. «Տրանսպորտային միջոցի կանգնեցման ձևը կայանման տեղերում»",
    "imageUrl": "https://varord.am/images/sign/n8/8_6_5.png",
    "type": "8. ԼՐԱՑՈՒՑԻՉ ՏԵՂԵԿԱՏՎՈՒԹՅԱՆ ՆՇԱՆՆԵՐ (ՑՈՒՑԱՆԱԿՆԵՐ)"
  },
  {
    "title": "8.6.6. «Տրանսպորտային միջոցի կանգնեցման ձևը կայանման տեղերում»",
    "description": "8.6.6. «Տրանսպորտային միջոցի կանգնեցման ձևը կայանման տեղերում»",
    "imageUrl": "https://varord.am/images/sign/n8/8_6_6.png",
    "type": "8. ԼՐԱՑՈՒՑԻՉ ՏԵՂԵԿԱՏՎՈՒԹՅԱՆ ՆՇԱՆՆԵՐ (ՑՈՒՑԱՆԱԿՆԵՐ)"
  },
  {
    "title": "8.6.7. «Տրանսպորտային միջոցի կանգնեցման ձևը կայանման տեղերում»",
    "description": "8.6.7. «Տրանսպորտային միջոցի կանգնեցման ձևը կայանման տեղերում»",
    "imageUrl": "https://varord.am/images/sign/n8/8_6_7.png",
    "type": "8. ԼՐԱՑՈՒՑԻՉ ՏԵՂԵԿԱՏՎՈՒԹՅԱՆ ՆՇԱՆՆԵՐ (ՑՈՒՑԱՆԱԿՆԵՐ)"
  },
  {
    "title": "8.6.8. «Տրանսպորտային միջոցի կանգնեցման ձևը կայանման տեղերում»",
    "description": "8.6.8. «Տրանսպորտային միջոցի կանգնեցման ձևը կայանման տեղերում»",
    "imageUrl": "https://varord.am/images/sign/n8/8_6_8.png",
    "type": "8. ԼՐԱՑՈՒՑԻՉ ՏԵՂԵԿԱՏՎՈՒԹՅԱՆ ՆՇԱՆՆԵՐ (ՑՈՒՑԱՆԱԿՆԵՐ)"
  },
  {
    "title": "8.6.9. «Տրանսպորտային միջոցի կանգնեցման ձևը կայանման տեղերում»",
    "description": "8.6.9. «Տրանսպորտային միջոցի կանգնեցման ձևը կայանման տեղերում»",
    "imageUrl": "https://varord.am/images/sign/n8/8_6_9.png",
    "type": "8. ԼՐԱՑՈՒՑԻՉ ՏԵՂԵԿԱՏՎՈՒԹՅԱՆ ՆՇԱՆՆԵՐ (ՑՈՒՑԱՆԱԿՆԵՐ)"
  },
  {
    "title": "8.7. «Կայանում չգործարկված շարժիչով». ցույց է տալիս, որ 6.4` «Կայանման տեղ»",
    "description": "8.7. «Կայանում չգործարկված շարժիչով». ցույց է տալիս, որ 6.4` «Կայանման տեղ»",
    "imageUrl": "https://varord.am/images/sign/n8/8_7.png",
    "type": "8. ԼՐԱՑՈՒՑԻՉ ՏԵՂԵԿԱՏՎՈՒԹՅԱՆ ՆՇԱՆՆԵՐ (ՑՈՒՑԱՆԱԿՆԵՐ)"
  },
  {
    "title": "8.8. «Վճարովի ծառայություններ»",
    "description": "8.8. «Վճարովի ծառայություններ»",
    "imageUrl": "https://varord.am/images/sign/n8/8_8.png",
    "type": "8. ԼՐԱՑՈՒՑԻՉ ՏԵՂԵԿԱՏՎՈՒԹՅԱՆ ՆՇԱՆՆԵՐ (ՑՈՒՑԱՆԱԿՆԵՐ)"
  },
  {
    "title": "8.9. «Կայանման տևողության սահմանափակում». տեղեկացնում է 6.4` «Կայանման տեղ»",
    "description": "8.9. «Կայանման տևողության սահմանափակում». տեղեկացնում է 6.4` «Կայանման տեղ»",
    "imageUrl": "https://varord.am/images/sign/n8/8_9.png",
    "type": "8. ԼՐԱՑՈՒՑԻՉ ՏԵՂԵԿԱՏՎՈՒԹՅԱՆ ՆՇԱՆՆԵՐ (ՑՈՒՑԱՆԱԿՆԵՐ)"
  },
  {
    "title": "8.10. «Ավտոմոբիլների զննման տեղ». ",
    "description": "8.10. «Ավտոմոբիլների զննման տեղ». ",
    "imageUrl": "https://varord.am/images/sign/n8/8_10.png",
    "type": "8. ԼՐԱՑՈՒՑԻՉ ՏԵՂԵԿԱՏՎՈՒԹՅԱՆ ՆՇԱՆՆԵՐ (ՑՈՒՑԱՆԱԿՆԵՐ)"
  },
  {
    "title": "8.11. «Թույլատրելի առավելագույն զանգվածի սահմանափակում»",
    "description": "8.11. «Թույլատրելի առավելագույն զանգվածի սահմանափակում»",
    "imageUrl": "https://varord.am/images/sign/n8/8_11.png",
    "type": "8. ԼՐԱՑՈՒՑԻՉ ՏԵՂԵԿԱՏՎՈՒԹՅԱՆ ՆՇԱՆՆԵՐ (ՑՈՒՑԱՆԱԿՆԵՐ)"
  },
  {
    "title": "8.12. «Վտանգավոր կողնակ». ",
    "description": "8.12. «Վտանգավոր կողնակ». ",
    "imageUrl": "https://varord.am/images/sign/n8/8_12.png",
    "type": "8. ԼՐԱՑՈՒՑԻՉ ՏԵՂԵԿԱՏՎՈՒԹՅԱՆ ՆՇԱՆՆԵՐ (ՑՈՒՑԱՆԱԿՆԵՐ)"
  },
  {
    "title": "8.13. «Գլխավոր ճանապարհի ուղղություն»",
    "description": "8.13. «Գլխավոր ճանապարհի ուղղություն»",
    "imageUrl": "https://varord.am/images/sign/n8/8_13.png",
    "type": "8. ԼՐԱՑՈՒՑԻՉ ՏԵՂԵԿԱՏՎՈՒԹՅԱՆ ՆՇԱՆՆԵՐ (ՑՈՒՑԱՆԱԿՆԵՐ)"
  },
  {
    "title": "8.14. «Երթևեկության գոտի»",
    "description": "8.14. «Երթևեկության գոտի»",
    "imageUrl": "https://varord.am/images/sign/n8/8_14.png",
    "type": "8. ԼՐԱՑՈՒՑԻՉ ՏԵՂԵԿԱՏՎՈՒԹՅԱՆ ՆՇԱՆՆԵՐ (ՑՈՒՑԱՆԱԿՆԵՐ)"
  },
  {
    "title": "8.15. «Կույր հետիոտներ».",
    "description": "8.15. «Կույր հետիոտներ».",
    "imageUrl": "https://varord.am/images/sign/n8/8_15.png",
    "type": "8. ԼՐԱՑՈՒՑԻՉ ՏԵՂԵԿԱՏՎՈՒԹՅԱՆ ՆՇԱՆՆԵՐ (ՑՈՒՑԱՆԱԿՆԵՐ)"
  },
  {
    "title": "8.16. «Խոնավ ծածկույթ»",
    "description": "8.16. «Խոնավ ծածկույթ»",
    "imageUrl": "https://varord.am/images/sign/n8/8_16.png",
    "type": "8. ԼՐԱՑՈՒՑԻՉ ՏԵՂԵԿԱՏՎՈՒԹՅԱՆ ՆՇԱՆՆԵՐ (ՑՈՒՑԱՆԱԿՆԵՐ)"
  },
  {
    "title": "8.17. «Հաշմանդամներ».",
    "description": "8.17. «Հաշմանդամներ».",
    "imageUrl": "https://varord.am/images/sign/n8/8_17.png",
    "type": "8. ԼՐԱՑՈՒՑԻՉ ՏԵՂԵԿԱՏՎՈՒԹՅԱՆ ՆՇԱՆՆԵՐ (ՑՈՒՑԱՆԱԿՆԵՐ)"
  },
  {
    "title": "8.18. «Բացի հաշմանդամներից». ",
    "description": "8.18. «Բացի հաշմանդամներից». ",
    "imageUrl": "https://varord.am/images/sign/n8/8_18.png",
    "type": "8. ԼՐԱՑՈՒՑԻՉ ՏԵՂԵԿԱՏՎՈՒԹՅԱՆ ՆՇԱՆՆԵՐ (ՑՈՒՑԱՆԱԿՆԵՐ)"
  },
  {
    "title": "8.19. «Վտանգավոր բեռի դասը». ",
    "description": "8.19. «Վտանգավոր բեռի դասը». ",
    "imageUrl": "https://varord.am/images/sign/n8/8_19.png",
    "type": "8. ԼՐԱՑՈՒՑԻՉ ՏԵՂԵԿԱՏՎՈՒԹՅԱՆ ՆՇԱՆՆԵՐ (ՑՈՒՑԱՆԱԿՆԵՐ)"
  },
  {
    "title": "8.20.1. «Տրանսպորտային միջոցի սայլակի տեսակը»",
    "description": "8.20.1. «Տրանսպորտային միջոցի սայլակի տեսակը»",
    "imageUrl": "https://varord.am/images/sign/n8/8_20_1.png",
    "type": "8. ԼՐԱՑՈՒՑԻՉ ՏԵՂԵԿԱՏՎՈՒԹՅԱՆ ՆՇԱՆՆԵՐ (ՑՈՒՑԱՆԱԿՆԵՐ)"
  },
  {
    "title": "8.20.2. «Տրանսպորտային միջոցի սայլակի տեսակը»",
    "description": "8.20.2. «Տրանսպորտային միջոցի սայլակի տեսակը»",
    "imageUrl": "https://varord.am/images/sign/n8/8_20_2.png",
    "type": "8. ԼՐԱՑՈՒՑԻՉ ՏԵՂԵԿԱՏՎՈՒԹՅԱՆ ՆՇԱՆՆԵՐ (ՑՈՒՑԱՆԱԿՆԵՐ)"
  },
  {
    "title": "8.21.1. «Ընդհանուր օգտագործման տրանսպորտային միջոցի տեսակը»",
    "description": "8.21.1. «Ընդհանուր օգտագործման տրանսպորտային միջոցի տեսակը»",
    "imageUrl": "https://varord.am/images/sign/n8/8_21_1.png",
    "type": "8. ԼՐԱՑՈՒՑԻՉ ՏԵՂԵԿԱՏՎՈՒԹՅԱՆ ՆՇԱՆՆԵՐ (ՑՈՒՑԱՆԱԿՆԵՐ)"
  },
  {
    "title": "8.21.2. «Ընդհանուր օգտագործման տրանսպորտային միջոցի տեսակը»",
    "description": "8.21.2. «Ընդհանուր օգտագործման տրանսպորտային միջոցի տեսակը»",
    "imageUrl": "https://varord.am/images/sign/n8/8_21_2.png",
    "type": "8. ԼՐԱՑՈՒՑԻՉ ՏԵՂԵԿԱՏՎՈՒԹՅԱՆ ՆՇԱՆՆԵՐ (ՑՈՒՑԱՆԱԿՆԵՐ)"
  },
  {
    "title": "8.21.3. «Ընդհանուր օգտագործման տրանսպորտային միջոցի տեսակը»",
    "description": "8.21.3. «Ընդհանուր օգտագործման տրանսպորտային միջոցի տեսակը»",
    "imageUrl": "https://varord.am/images/sign/n8/8_21_3.png",
    "type": "8. ԼՐԱՑՈՒՑԻՉ ՏԵՂԵԿԱՏՎՈՒԹՅԱՆ ՆՇԱՆՆԵՐ (ՑՈՒՑԱՆԱԿՆԵՐ)"
  },
  {
    "title": "8.22.1. «Խոչընդոտ»",
    "description": "8.22.1. «Խոչընդոտ»",
    "imageUrl": "https://varord.am/images/sign/n8/8_22_1.png",
    "type": "8. ԼՐԱՑՈՒՑԻՉ ՏԵՂԵԿԱՏՎՈՒԹՅԱՆ ՆՇԱՆՆԵՐ (ՑՈՒՑԱՆԱԿՆԵՐ)"
  },
  {
    "title": "8.22.2. «Խոչընդոտ»",
    "description": "8.22.2. «Խոչընդոտ»",
    "imageUrl": "https://varord.am/images/sign/n8/8_22_2.png",
    "type": "8. ԼՐԱՑՈՒՑԻՉ ՏԵՂԵԿԱՏՎՈՒԹՅԱՆ ՆՇԱՆՆԵՐ (ՑՈՒՑԱՆԱԿՆԵՐ)"
  },
  {
    "title": "8.22.3. «Խոչընդոտ»",
    "description": "8.22.3. «Խոչընդոտ»",
    "imageUrl": "https://varord.am/images/sign/n8/8_22_3.png",
    "type": "8. ԼՐԱՑՈՒՑԻՉ ՏԵՂԵԿԱՏՎՈՒԹՅԱՆ ՆՇԱՆՆԵՐ (ՑՈՒՑԱՆԱԿՆԵՐ)"
  },
  {
    "title": "8.23. «Աշխատում է տարհանիչը»",
    "description": "8.23. «Աշխատում է տարհանիչը»",
    "imageUrl": "https://varord.am/images/sign/n8/8_23.png",
    "type": "8. ԼՐԱՑՈՒՑԻՉ ՏԵՂԵԿԱՏՎՈՒԹՅԱՆ ՆՇԱՆՆԵՐ (ՑՈՒՑԱՆԱԿՆԵՐ)"
  },
  {
    "title": "8.24. «Ծառայողական ավտոմոբիլների համար կայանատեղ»",
    "description": "8.24. «Ծառայողական ավտոմոբիլների համար կայանատեղ»",
    "imageUrl": "https://varord.am/images/sign/n8/8_24.png",
    "type": "8. ԼՐԱՑՈՒՑԻՉ ՏԵՂԵԿԱՏՎՈՒԹՅԱՆ ՆՇԱՆՆԵՐ (ՑՈՒՑԱՆԱԿՆԵՐ)"
  },
  {
    "title": "8.25. «Բացի ծառայողական ավտոմոբիլներից»",
    "description": "8.25. «Բացի ծառայողական ավտոմոբիլներից»",
    "imageUrl": "https://varord.am/images/sign/n8/8_25.png",
    "type": "8. ԼՐԱՑՈՒՑԻՉ ՏԵՂԵԿԱՏՎՈՒԹՅԱՆ ՆՇԱՆՆԵՐ (ՑՈՒՑԱՆԱԿՆԵՐ)"
  },
  {
    "title": "8.26. «Զբոսաշրջային ավտոբուսների համար կայանատեղի»",
    "description": "8.26. «Զբոսաշրջային ավտոբուսների համար կայանատեղի»",
    "imageUrl": "https://varord.am/images/sign/n8/8_26.png",
    "type": "8. ԼՐԱՑՈՒՑԻՉ ՏԵՂԵԿԱՏՎՈՒԹՅԱՆ ՆՇԱՆՆԵՐ (ՑՈՒՑԱՆԱԿՆԵՐ)"
  },
  {
    "title": "8.27. «Բացի զբոսաշրջային ավտոբուսներից»",
    "description": "8.27. «Բացի զբոսաշրջային ավտոբուսներից»",
    "imageUrl": "https://varord.am/images/sign/n8/8_27.png",
    "type": "8. ԼՐԱՑՈՒՑԻՉ ՏԵՂԵԿԱՏՎՈՒԹՅԱՆ ՆՇԱՆՆԵՐ (ՑՈՒՑԱՆԱԿՆԵՐ)"
  },
  {
    "title": "8.28. «Շրջիկ առևտուր իրականացնող տրանսպորտային միջոցների համար կայանատեղի»",
    "description": "8.28. «Շրջիկ առևտուր իրականացնող տրանսպորտային միջոցների համար կայանատեղի»",
    "imageUrl": "https://varord.am/images/sign/n8/8_28.png",
    "type": "8. ԼՐԱՑՈՒՑԻՉ ՏԵՂԵԿԱՏՎՈՒԹՅԱՆ ՆՇԱՆՆԵՐ (ՑՈՒՑԱՆԱԿՆԵՐ)"
  }
]
